Workbook

Sheet Fahad
A1: Tester : | B1: Mohammed Fahad Faisal
A2: Project Name: | B2: Parent Bridge
A3: Developer: | B3: AI Hunter
A4: OS: | B4: Windows 11 Pro Version:24H2 OS build:26100.4946
A5: Environment: | B5: Brave 1.81.135 (Official Build) (64-bit) Chromium: 139.0.7258.127 | N5: Place solve if the issue resolves | \/ | O5: Mention which Stack solved the issue | \/
A7: Test ID | B7: Module | C7: Sub Module | D7: Test Case Description | E7: Preconditions | F7: Test Steps | G7: Test Data | H7: Expected Result | I7: Actual Result | J7: Status | K7: Severity | L7: Screen Shots | M7: Suggestion | N7: Feedback | O7: Stack | P7: Comment
A8: BR_001 | B8: Splash Screen | C8: Splash Screen | D8: "Next Button" is not implemented | E8: User need to able to access website using browser | F8: 1. Open website of ParentBridge | G8: N/A | H8: User should be able to change pages by sliding right to left or click button | I8: Unable to change page screen | J8: Fail | K8: Medium | L8: 001.png | N8: Solved | O8: Front-End | P8: Splash screen is removed
A10: BR_002 | B10: Splash Screen | C10: Splash Screen | D10: A blank space has been spotted on the splash screen. | E10: User need to able to access website using browser | F10: 1. Open website of ParentBridge | G10: N/A | H10: The screen should be filled with the necessary information. | I10: A blank space has been noticed on the splash screen. | J10: Fail | K10: Medium | L10: 002.png | N10: Solved | O10: Front-End | P10: Splash screen is removed
A12: BR_003 | B12: Login | C12: Forget Password | D12: The forgot password section failed to display the correct error message. | E12: User need to able to access website using browser | F12: 1. Open website of ParentBridge 2. Goto Login Page 3. Click on Forget Password | G12: N/A | H12: The error should clearly display the exact problem. | I12: The user was not found in the database, and the system returned a 400 error code, which doesn’t seem accurate from the user’s side. | J12: Fail | K12: High | L12: 003.png | N12: Solved | O12: Front-End
A14: BR_004 | B14: Signup | C14: Signup | D14: Failed to signup using google signin | E14: User need to able to access website using browser | F14: 1. Open website of ParentBridge 2. Goto Login Page 3. Click on SignUp | G14: N/A | H14: User should be able to signup through google signup | I14: Unable to sign up using Google. | J14: Fail | K14: High | L14: 004.png | N14: Solved | O14: Front-End
A16: BR_005 | B16: Signup | C16: OTP | D16: Able to signup with expired OTP | E16: User need to able to access website using browser | F16: 1. Open website of ParentBridge 2. Goto Login Page 3. Click on SignUp 4. Enter expired OTP and click on verify | G16: USER CREDENTIAL | H16: User shouldn’t be able to verify their login credentials using an expired OTP. | I16: Users can verify their profile using an expired OTP. | J16: Fail | K16: High | L16: 005.mp4 | N16: Solved | O16: Front-End
A18: BR_006 | B18: Onboarding | C18: Onboarding | D18: Secure route has not been implemented yet. | E18: User need to able to access website using browser | F18: 1. Open website of ParentBridge 2. Goto Login Page 3. Goto /accout-setup route | G18: USER CREDENTIAL | H18: Users should not be allowed to change the route manually. | I18: User can manually change the route, which could raise security concerns. | J18: Fail | K18: High | L18: 006.mp4 | N18: Solved | O18: Front-End
A20: BR_007 | B20: Basic Info | C20: Basic Info | D20: The required mark on basic information should be displayed correctly. | E20: User need to able to access website using browser | F20: 1. Open website of ParentBridge 2. Goto Login Page 3. Login using valid credentials | G20: USER CREDENTIAL | H20: A required mark should be placed in the input field. | I20: Required field are not mentioned. | J20: Fail | K20: Medium | L20: 007.png | N20: Solved | O20: Front-End
A22: BR_008 | B22: Basic Info | C22: Basic Info | D22: Character limit hasn’t been implemented. | E22: User need to able to access website using browser | F22: 1. Open website of ParentBridge 2. Goto Login Page 3. Login using valid credentials | G22: USER CREDENTIAL | H22: The input field should allow users to enter only a limited number of characters. | I22: Can enter an unlimited number of characters in the input field. | J22: Fail | K22: Low | L22: 008.png | N22: Solved | O22: Front-End
A24: BR_009 | B24: Basic Info | C24: Basic Info | D24: Data validation problem in the basic information. | E24: User need to able to access website using browser | F24: 1. Open website of ParentBridge 2. Goto Login Page 3. Login using valid credentials | G24: USER CREDENTIAL | H24: Character field should only accept letters, while the number field should only accept numeric values. | I24: Data input validation hasn’t been implemented. | J24: Fail | K24: High | L24: 009.png | N24: Solved | O24: Front-End
A26: BR_010 | B26: Subscription | C26: Subscription | D26: Calculation error has been noticed in ParentBridge Pro plan | E26: User need to able to access website using browser | F26: 1. Open website of ParentBridge 2. Goto Login Page 3. Login using valid credentials 4. Fill up Basic information | G26: USER CREDENTIAL | H26: The price plan calculation needs to be accurate on the frontend. | I26: Miscalculation in the monthly and yearly plan has been noticed. | J26: Fail | K26: High | L26: 010.png | M26: Add discount rate | N26: Unsolved | O26: Front-End | P26: The whole pricing is controlled from the backend only.
A28: BR_011 | B28: Subscription | C28: Subscription | D28: Calculation error has been noticed in ParentBridge Pro Plus plan | E28: User need to able to access website using browser | F28: 1. Open website of ParentBridge 2. Goto Login Page 3. Login using valid credentials 4. Fill up Basic information | G28: USER CREDENTIAL | H28: The price plan calculation needs to be accurate on the frontend. | I28: Miscalculation in the monthly and yearly plan has been noticed. | J28: Fail | K28: High | L28: 011.png | M28: Add discount rate | N28: Unsolved | O28: Front-End | P28: The whole pricing is controlled from the backend only.
A30: BR_012 | B30: Subscription | C30: Subscription | D30: Can't buy the plan | E30: User need to able to access website using browser | F30: 1. Open website of ParentBridge 2. Goto Login Page 3. Login using valid credentials 4. Fill up Basic information 5. Click next and goto subscription page | G30: USER CREDENTIAL | H30: Users should not encounter errors when purchasing a plan. | I30: Unable to complete plan purchase | J30: Fail | K30: High | L30: 012.png | M30: Add discount rate | N30: Solved | O30: Front-End
A32: BR_013 | B32: Subscription | C32: Subscription | D32: Checkout page redirect to localhost url | E32: User need to able to access website using browser | F32: 1. Open website of ParentBridge 2. Goto Login Page 3. Login using valid credentials 4. Fill up Basic information 5. Click next and goto subscription page | G32: USER CREDENTIAL | H32: After purchasing a plan, the user should be redirected to either the home page or the payment success page. | I32: After purchasing a plan, the user wasn’t redirected to the home page or the payment success page. | J32: Fail | K32: High | L32: 013.png | N32: Solved
A34: BR_014 | B34: Home | C34: Chat | D34: A non-functional button has been noticed. | E34: User need to able to access website using browser | F34: 1. Open website of ParentBridge 2. Login using valid credential 3. goto chat | G34: USER CREDENTIAL | H34: The settings button and options should be accessible in the chat section. | I34: Chat options are missing in the frontend. | J34: Fail | K34: Medium | L34: 014.png | N34: Solved | O34: Front-End
A36: BR_015 | B36: Home | C36: Home | D36: Quick access settings button isn’t working. | E36: User need to able to access website using browser | F36: 1. Open website of ParentBridge 2. Login using valid credential 3. goto Home 4. goto quick access section | G36: USER CREDENTIAL | H36: User should be able to set quick access manually | I36: Quick access setup failed on the user’s side. | J36: Fail | K36: Medium | L36: 015.png | N36: Solved | O36: Front-End
A38: BR_016 | B38: Home | C38: Home | D38: Failed to redirect user to calender | E38: User need to able to access website using browser | F38: 1. Open website of ParentBridge 2. Login using valid credential 3. goto Home 4. goto up comming events section | G38: USER CREDENTIAL | H38: User should be redirected to the desired page when clicking the quick access links | I38: Could not redirect the user to the intended location. | J38: Fail | K38: High | L38: 016.png | N38: Solved | O38: Front-End
A40: BR_017 | B40: Home | C40: Calls | D40: Unable to connect with co-parent | E40: User need to able to access website using browser | F40: 1. Open website of ParentBridge 2. Login using valid credential 3. goto Home 4. goto up comming events section | G40: USER CREDENTIAL | H40: Users should have the option to add co-parents right after creating an account or choose to add them later. | I40: Couldn’t add a co-parent after setting up the account. | J40: Fail | K40: High | L40: 017.png | N40: Solved | O40: Front-End, Back-End
A42: BR_018 | B42: Home | C42: Calendar | D42: Children are given default names whenever a different name is entered. | E42: User need to able to access website using browser | F42: 1. Open website of ParentBridge 2. Login using valid credential 3. goto Home 4. Click on calender | G42: USER CREDENTIAL | H42: Should display the child's name that is entered. | I42: Default child names are showing up even when they haven’t been entered. | J42: Fail | K42: Medium | L42: 018.png | N42: Solved | O42: Front-End, Back-End
A44: BR_019 | B44: Home | C44: Calendar | D44: Can set an event in the past. | E44: User need to able to access website using browser | F44: 1. Open website of ParentBridge 2. Login using valid credential 3. goto Home 4. Click on calender | G44: USER CREDENTIAL | H44: Users shouldn’t be able to mark past events on the calendar to avoid any misunderstanding issues. | I44: User is able to set mark on past event | J44: Fail | K44: Medium | L44: 019.png | M44: Need to discuss this matter with client to avoid miss-understanding between co-parent | N44: Unsolved | O44: Back-End | P44: If backend will fix this problem then in my frontend, it wont show the past event.
A46: BR_020 | B46: Home | C46: Calendar | D46: Calendar navigation arrow missing in the frontend | E46: User need to able to access website using browser | F46: 1. Open website of ParentBridge 2. Login using valid credential 3. goto Home 4. Click on calender | G46: USER CREDENTIAL | H46: The calendar navigation arrow should be positioned to allow viewing of past events. | I46: Missing navigation arrow in calendar | J46: Fail | K46: Medium | L46: 020.png | N46: Solved | O46: Front-End
A48: BR_021 | B48: Home | C48: Calendar | D48: Date wise event view failed | E48: User need to able to access website using browser | F48: 1. Open website of ParentBridge 2. Login using valid credential 3. goto Home 4. Click on calender | G48: USER CREDENTIAL | H48: Event number under the date should be implemented according to the Figma requirements. | I48: Event number under the date is missing on the frontend. | J48: Fail | K48: High | L48: 021.png | N48: Solved | O48: Front-End
A50: BR_022 | B50: Home | C50: Calendar | D50: Failed to add holiday planner to calendar. | E50: User need to able to access website using browser | F50: 1. Open website of ParentBridge 2. Login using valid credential 3. goto Home 4. Click on calender | G50: USER CREDENTIAL | H50: Users should be able to add a holiday planner to their calendar. | I50: Couldn’t add the holiday planner to the calendar section. | J50: Fail | K50: High | L50: 022.png | N50: Solved | O50: Front-End
A52: BR_023 | B52: Home | C52: Documents | D52: Can't upload document on the frontend. | E52: User need to able to access website using browser | F52: 1. Open website of ParentBridge 2. Login using valid credential 3. goto Home 4. Click on calender | G52: USER CREDENTIAL | H52: User should be able to upload a document without any issues. | I52: Unable to upload document. | J52: Fail | K52: High | L52: 023.png | N52: Solved | O52: Front-End | P52: The images and the pdf is not showing in the website because backend is using local base url
A54: BR_024 | B54: Home | C54: Calendar | D54: All-day event toggle button is missing from the frontend. | E54: User need to able to access website using browser | F54: 1. Open website of ParentBridge 2. Login using valid credential 3. goto Home 4. Click on calender 5. Click on add event | G54: USER CREDENTIAL | H54: Feature should be available as shown in Figma. | I54: All-day event button is missing in the frontend | J54: Fail | K54: High | L54: 024.png | N54: Solved | O54: Front-End
A56: BR_025 | B56: Signup | C56: Signup | D56: Dull color theme of the signup button makes users think it’s not clickable. | E56: User need to able to access website using browser | F56: 1. Open website of ParentBridge 2. Goto Login Page 3. Click on SignUp | G56: N/A | H56: Button color should be bright from the user's perspective. | I56: Signup button uses a dull color. | J56: Fail | K56: Low | L56: 025.png | N56: Solved | O56: Back-End | P56: It is handled by backend
A58: BR_026 | B58: Subscription | C58: Subscription | D58: Yearly subscription failed on both plans. | E58: User need to able to access website using browser | F58: 1. Open website of ParentBridge 2. Goto Login Page 3. Login using valid credentials 4. Fill up Basic information 5. Click next and goto subscription page | G58: USER CREDENTIAL | H58: Users should be to purchase a monthly or yearly plan on both subscriptions without any issues. | I58: Unable to complete the purchase of the yearly subscription for either. | J58: Fail | K58: High | L58: 026.png | N58: Solved | O58: Back-End | P58: It is handled by backend
A60: BR_027 | B60: Subscription | C60: Subscription | D60: After purchasing a plan, it should redirect to the home or dashboard page. | E60: User need to able to access website using browser | F60: 1. Open website of ParentBridge 2. Goto Login Page 3. Login using valid credentials 4. Fill up Basic information 5. Click next and goto subscription page | G60: USER CREDENTIAL | H60: After a successful purchase, the user should be redirected to the home or dashboard page. | I60: Redirecting to the subscription page doesn’t make sense. | J60: Fail | K60: Medium | L60: 027.png | N60: Solved | O60: Front-End
A62: BR_028 | B62: Subscription | C62: Subscription | D62: Purchased a yearly plan, but it shows that both the monthly and yearly plans are active. | E62: User need to able to access website using browser | F62: 1. Open website of ParentBridge 2. Goto Login Page 3. Login using valid credentials 4. Fill up Basic information 5. Click next and goto subscription page | G62: USER CREDENTIAL | H62: If the subscription card contains both monthly and yearly data, then when a user purchases a yearly plan, it should not display the current plan as active under the monthly data. | I62: Displays both monthly and yearly plans as active on a single subscription card. | J62: Fail | K62: High | L62: 028.png | N62: Solved | O62: Front-End
A64: BR_029 | B64: Settings | C64: Profile Information | D64: Email field missing in profile information tab | E64: User need to able to access website using browser | F64: 1. Open website of ParentBridge 2. Login using valid credentials 3. click on settings 4. click on profile information | G64: USER CREDENTIAL | H64: Email field should be visible in the profile information. | I64: Email name field is missing in the profile information section. | J64: Fail | K64: Medium | L64: 029.png | N64: Unsolved | O64: Back-End | P64: Email is not coming in profile api
A66: BR_030 | B66: Home | C66: Settings | D66: Logout button should be positioned in the left section. | E66: User need to able to access website using browser | F66: 1. Open website of ParentBridge 2. Login using valid credentials 3. click on settings | G66: USER CREDENTIAL | H66: Logout button should be placed below the sidebar for convenient access. | I66: Logout button is under setting tab | J66: Fail | K66: Medium | L66: 030.png | N66: Solved | O66: Front-End
A68: BR_031 | B68: Home | C68: Home | D68: Responsiveness didn’t work. | E68: User need to able to access website using browser | F68: 1. Open website of ParentBridge 2. Login using valid credentials | G68: USER CREDENTIAL | H68: Web app should be responsive and adapt seamlessly to any device. | I68: Sidebar failed to display responsive mode. | J68: Fail | K68: High | L68: 031.png | N68: Solved | O68: Front-End
A70: BR_032 | B70: Settings | C70: Profile Information | D70: Co-parent's contact number is not showing up in the user’s co-parent information section. | E70: User need to able to access website using browser | F70: 1. Open website of ParentBridge 2. Login using valid credentials 3. click on settings 4. click on co-parent information | G70: USER CREDENTIAL | H70: Contact should be displayed in both parents' profiles | I70: Co-parent’s profile is missing a contact number. | J70: Fail | K70: High | L70: 032.png | N70: Unsolved | O70: Back-End | P70: Backend, please check this issue because I am showing all the fields properly
A72: BR_033 | B72: Home | C72: Expense | D72: Placeholder text color blends with the background, making it hard to read. | E72: User need to able to access website using browser | F72: 1. Open website of ParentBridge 2. Login using valid credentials 3. click on expense | G72: USER CREDENTIAL | H72: Placeholder text should be in the opposite color of the background for better visibility and user understanding. | I72: Background color and the placeholder text color are the same, making it difficult to read the text. | J72: Fail | K72: Medium | L72: 033.png | N72: Solved | O72: Front-End
A74: BR_034 | B74: Home | C74: Expense | D74: Export feature hasn’t been added yet. | E74: User need to able to access website using browser | F74: 1. Open website of ParentBridge 2. Login using valid credentials 3. click on expense | G74: USER CREDENTIAL | H74: Export feature should be implemented according to the Figma design. | I74: Export feature is missing on the web. | J74: Fail | K74: High | L74: 034.png | N74: Unsolved | O74: Back-End | P74: Export feature is not implmeneted in backend
A76: BR_035 | B76: Home | C76: Expense | D76: Parent and co-parent expenses are not displayed correctly. | E76: User need to able to access website using browser | F76: 1. Open website of ParentBridge 2. Login using valid credentials 3. click on expense | G76: USER CREDENTIAL | H76: Expenses should be displayed accurately. | I76: Mismatch has been noticed between the parent and co-parent expense data. | J76: Fail | K76: High | L76: 035.png | N76: Unsolved | O76: Back-End | P76: Backend is not giving the data
A78: BR_036 | B78: Home | C78: Expense | D78: Display issue with the total expense calculation has been noticed. | E78: User need to able to access website using browser | F78: 1. Open website of ParentBridge 2. Login using valid credentials 3. click on expense | G78: USER CREDENTIAL | H78: Calculated amount should be accurately displayed. | I78: Miscalculation has been spotted in the expense tab. | J78: Fail | K78: High | L78: 036.png | N78: Unsolved | O78: Back-End | P78: Backend needs to be fixed.
A80: BR_037 | B80: Settings | C80: Profile Information | D80: Name, state, and phone are typically required to create an account, but you can still set one up without them. | E80: User need to able to access website using browser | F80: 1. Open website of ParentBridge 2. Login using valid credentials 3. click on settings 4. click on co-parent information | G80: USER CREDENTIAL | H80: Profile setup page should include the required field. | I80: Required fields are not being captured during profile setup. | J80: Fail | K80: High | L80: 037.png | N80: Unsolved | P80: User cant create account without account setup
A82: BR_038 | B82: Settings | C82: Help and Support | D82: Call support is not integrated yet. | E82: User need to able to access website using browser | F82: 1. Open website of ParentBridge 2. Login using valid credentials 3. click on settings 4. click on Help and Support | G82: USER CREDENTIAL | H82: Call support button should be implemented flawlessly. | I82: Call support feature hasn’t been set up yet. | J82: Fail | K82: High | L82: 038.png | N82: Unsolved | P82: I need the support phone number
A84: BR_039 | B84: Settings | C84: Help and Support | D84: Email support hasn’t been set up yet. | E84: User need to able to access website using browser | F84: 1. Open website of ParentBridge 2. Login using valid credentials 3. click on settings 4. click on Help and Support | G84: USER CREDENTIAL | H84: Email support should be implemented precisely. | I84: Feature hasn't been implemented yet. | J84: Fail | K84: High | L84: 039.png | N84: Unsolved | P84: I need teh support email address
A86: BR_040 | B86: Settings | C86: Help and Support | D86: Live chat support hasn’t been set up yet. | E86: User need to able to access website using browser | F86: 1. Open website of ParentBridge 2. Login using valid credentials 3. click on settings 4. click on Help and Support | G86: USER CREDENTIAL | H86: Live chat support should be implemented precisely. | I86: Feature hasn't been implemented yet. | J86: Fail | K86: High | L86: 040.png | N86: Solved | P86: Its not in figma so I removed it
A88: BR_041
A90: BR_042
A92: BR_043
A94: BR_044

Sheet Tahsin
A2: Tester : | D2: Severity | E2: Issues
A3: Project Name: | D3: High | E3: =COUNTIF(K14:K897, "High") -> 0
A4: Project URL: | D4: Medium | E4: =COUNTIF(K14:K898, "Medium") -> 0
A5: Developer: | D5: Low | E5: =COUNTIF(K14:K899, "Low") -> 0
A6: OS:
A7: Environment | D7: Total Test Cases: | E7: =SUM(E3:E5) -> 0
D8: Test Case Solved :
A10: Test ID | B10: Module | C10: Sub Module | D10: Test Case Description | E10: Preconditions | F10: Test Steps | G10: Test Data | H10: Expected Result | I10: Actual Result | J10: Status | K10: Severity | L10: Screen Shots | M10: Suggestion | N10: Feedback | O10: Stack | P10: Comment

Sheet Summary Report
A1: Module | B1: Sub Module | C1: Test Case ID | D1: Bug Count | E1: Bug Rate % | F1: Bug Severity
A2: =IFERROR(__xludf.DUMMYFUNCTION("SORT( SPLIT( UNIQUE( FILTER('Main Report'!B11:B100 & ""♦"" & 'Main Report'!C11:C100, LEN('Main Report'!C11:C100)) ), ""♦"" ), 1, TRUE, 2, TRUE ) "),"Basic Info") -> Basic Info | B2: =IFERROR(__xludf.DUMMYFUNCTION("""COMPUTED_VALUE"""),"Basic Info") -> Basic Info | C2: =IFERROR(__xludf.DUMMYFUNCTION("TEXTJOIN("", "", TRUE, FILTER('Main Report'!A11:A100, ('Main Report'!B11:B100=A2) * ('Main Report'!C11:C100=B2) ) ) "),"BR-001, BR-002, BR-003") -> BR-001, BR-002, BR-003 | D2: =IFERROR(__xludf.DUMMYFUNCTION("COUNTA(UNIQUE(TRANSPOSE(SPLIT(C2, "", "")))) "),3.0) -> 3 | E2: =IF(D2="", "", TEXT((D2 / 'Main Report'!$E$7), "0.00%")) -> 7.50% | F2: =IFERROR(__xludf.DUMMYFUNCTION("IF(C2="""", """", TEXTJOIN("", "", TRUE, ""High: "" & COUNTIF(FILTER('Main Report'!K11:K100, ISNUMBER(MATCH('Main Report'!A11:A100, SPLIT(C2, "", ""), 0))), ""High"") & CHAR(10) & ""Medium: "" & COUNTIF(FILTER('Main Report'!K11:K100, ISNU"&"MBER(MATCH('Main Report'!A11:A100, SPLIT(C2, "", ""), 0))), ""Medium"") & CHAR(10) & ""Low: "" & COUNTIF(FILTER('Main Report'!K11:K100, ISNUMBER(MATCH('Main Report'!A11:A100, SPLIT(C2, "", ""), 0))), ""Low"") ) ) "),"High: 1 Medium: 1 Low: 1") -> High: 1 Medium: 1 Low: 1
A3: =IFERROR(__xludf.DUMMYFUNCTION("""COMPUTED_VALUE"""),"Home") -> Home | B3: =IFERROR(__xludf.DUMMYFUNCTION("""COMPUTED_VALUE"""),"Calendar") -> Calendar | C3: =IFERROR(__xludf.DUMMYFUNCTION("TEXTJOIN("", "", TRUE, FILTER('Main Report'!A12:A101, ('Main Report'!B12:B101=A3) * ('Main Report'!C12:C101=B3) ) ) "),"BR-004, BR-005, BR-006, BR-007, BR-008, BR-009") -> BR-004, BR-005, BR-006, BR-007, BR-008, BR-009 | D3: =IFERROR(__xludf.DUMMYFUNCTION("COUNTA(UNIQUE(TRANSPOSE(SPLIT(C3, "", "")))) "),6.0) -> 6 | E3: =IF(D3="", "", TEXT((D3 / 'Main Report'!$E$7), "0.00%")) -> 15.00% | F3: =IFERROR(__xludf.DUMMYFUNCTION("IF(C3="""", """", TEXTJOIN("", "", TRUE, ""High: "" & COUNTIF(FILTER('Main Report'!K12:K101, ISNUMBER(MATCH('Main Report'!A12:A101, SPLIT(C3, "", ""), 0))), ""High"") & CHAR(10) & ""Medium: "" & COUNTIF(FILTER('Main Report'!K12:K101, ISNU"&"MBER(MATCH('Main Report'!A12:A101, SPLIT(C3, "", ""), 0))), ""Medium"") & CHAR(10) & ""Low: "" & COUNTIF(FILTER('Main Report'!K12:K101, ISNUMBER(MATCH('Main Report'!A12:A101, SPLIT(C3, "", ""), 0))), ""Low"") ) ) "),"High: 3 Medium: 3 Low: 0") -> High: 3 Medium: 3 Low: 0
A4: =IFERROR(__xludf.DUMMYFUNCTION("""COMPUTED_VALUE"""),"Home") -> Home | B4: =IFERROR(__xludf.DUMMYFUNCTION("""COMPUTED_VALUE"""),"Calls") -> Calls | C4: =IFERROR(__xludf.DUMMYFUNCTION("TEXTJOIN("", "", TRUE, FILTER('Main Report'!A13:A102, ('Main Report'!B13:B102=A4) * ('Main Report'!C13:C102=B4) ) ) "),"BR-010") -> BR-010 | D4: =IFERROR(__xludf.DUMMYFUNCTION("COUNTA(UNIQUE(TRANSPOSE(SPLIT(C4, "", "")))) "),1.0) -> 1 | E4: =IF(D4="", "", TEXT((D4 / 'Main Report'!$E$7), "0.00%")) -> 2.50% | F4: =IFERROR(__xludf.DUMMYFUNCTION("IF(C4="""", """", TEXTJOIN("", "", TRUE, ""High: "" & COUNTIF(FILTER('Main Report'!K13:K102, ISNUMBER(MATCH('Main Report'!A13:A102, SPLIT(C4, "", ""), 0))), ""High"") & CHAR(10) & ""Medium: "" & COUNTIF(FILTER('Main Report'!K13:K102, ISNU"&"MBER(MATCH('Main Report'!A13:A102, SPLIT(C4, "", ""), 0))), ""Medium"") & CHAR(10) & ""Low: "" & COUNTIF(FILTER('Main Report'!K13:K102, ISNUMBER(MATCH('Main Report'!A13:A102, SPLIT(C4, "", ""), 0))), ""Low"") ) ) "),"High: 1 Medium: 0 Low: 0") -> High: 1 Medium: 0 Low: 0
A5: =IFERROR(__xludf.DUMMYFUNCTION("""COMPUTED_VALUE"""),"Home") -> Home | B5: =IFERROR(__xludf.DUMMYFUNCTION("""COMPUTED_VALUE"""),"Chat") -> Chat | C5: =IFERROR(__xludf.DUMMYFUNCTION("TEXTJOIN("", "", TRUE, FILTER('Main Report'!A14:A103, ('Main Report'!B14:B103=A5) * ('Main Report'!C14:C103=B5) ) ) "),"BR-011") -> BR-011 | D5: =IFERROR(__xludf.DUMMYFUNCTION("COUNTA(UNIQUE(TRANSPOSE(SPLIT(C5, "", "")))) "),1.0) -> 1 | E5: =IF(D5="", "", TEXT((D5 / 'Main Report'!$E$7), "0.00%")) -> 2.50% | F5: =IFERROR(__xludf.DUMMYFUNCTION("IF(C5="""", """", TEXTJOIN("", "", TRUE, ""High: "" & COUNTIF(FILTER('Main Report'!K14:K103, ISNUMBER(MATCH('Main Report'!A14:A103, SPLIT(C5, "", ""), 0))), ""High"") & CHAR(10) & ""Medium: "" & COUNTIF(FILTER('Main Report'!K14:K103, ISNU"&"MBER(MATCH('Main Report'!A14:A103, SPLIT(C5, "", ""), 0))), ""Medium"") & CHAR(10) & ""Low: "" & COUNTIF(FILTER('Main Report'!K14:K103, ISNUMBER(MATCH('Main Report'!A14:A103, SPLIT(C5, "", ""), 0))), ""Low"") ) ) "),"High: 0 Medium: 1 Low: 0") -> High: 0 Medium: 1 Low: 0
A6: =IFERROR(__xludf.DUMMYFUNCTION("""COMPUTED_VALUE"""),"Home") -> Home | B6: =IFERROR(__xludf.DUMMYFUNCTION("""COMPUTED_VALUE"""),"Documents") -> Documents | C6: =IFERROR(__xludf.DUMMYFUNCTION("TEXTJOIN("", "", TRUE, FILTER('Main Report'!A15:A104, ('Main Report'!B15:B104=A6) * ('Main Report'!C15:C104=B6) ) ) "),"BR-012") -> BR-012 | D6: =IFERROR(__xludf.DUMMYFUNCTION("COUNTA(UNIQUE(TRANSPOSE(SPLIT(C6, "", "")))) "),1.0) -> 1 | E6: =IF(D6="", "", TEXT((D6 / 'Main Report'!$E$7), "0.00%")) -> 2.50% | F6: =IFERROR(__xludf.DUMMYFUNCTION("IF(C6="""", """", TEXTJOIN("", "", TRUE, ""High: "" & COUNTIF(FILTER('Main Report'!K15:K104, ISNUMBER(MATCH('Main Report'!A15:A104, SPLIT(C6, "", ""), 0))), ""High"") & CHAR(10) & ""Medium: "" & COUNTIF(FILTER('Main Report'!K15:K104, ISNU"&"MBER(MATCH('Main Report'!A15:A104, SPLIT(C6, "", ""), 0))), ""Medium"") & CHAR(10) & ""Low: "" & COUNTIF(FILTER('Main Report'!K15:K104, ISNUMBER(MATCH('Main Report'!A15:A104, SPLIT(C6, "", ""), 0))), ""Low"") ) ) "),"High: 1 Medium: 0 Low: 0") -> High: 1 Medium: 0 Low: 0
A7: =IFERROR(__xludf.DUMMYFUNCTION("""COMPUTED_VALUE"""),"Home") -> Home | B7: =IFERROR(__xludf.DUMMYFUNCTION("""COMPUTED_VALUE"""),"Expense") -> Expense | C7: =IFERROR(__xludf.DUMMYFUNCTION("TEXTJOIN("", "", TRUE, FILTER('Main Report'!A16:A105, ('Main Report'!B16:B105=A7) * ('Main Report'!C16:C105=B7) ) ) "),"BR-013, BR-014, BR-015, BR-016") -> BR-013, BR-014, BR-015, BR-016 | D7: =IFERROR(__xludf.DUMMYFUNCTION("COUNTA(UNIQUE(TRANSPOSE(SPLIT(C7, "", "")))) "),4.0) -> 4 | E7: =IF(D7="", "", TEXT((D7 / 'Main Report'!$E$7), "0.00%")) -> 10.00% | F7: =IFERROR(__xludf.DUMMYFUNCTION("IF(C7="""", """", TEXTJOIN("", "", TRUE, ""High: "" & COUNTIF(FILTER('Main Report'!K16:K105, ISNUMBER(MATCH('Main Report'!A16:A105, SPLIT(C7, "", ""), 0))), ""High"") & CHAR(10) & ""Medium: "" & COUNTIF(FILTER('Main Report'!K16:K105, ISNU"&"MBER(MATCH('Main Report'!A16:A105, SPLIT(C7, "", ""), 0))), ""Medium"") & CHAR(10) & ""Low: "" & COUNTIF(FILTER('Main Report'!K16:K105, ISNUMBER(MATCH('Main Report'!A16:A105, SPLIT(C7, "", ""), 0))), ""Low"") ) ) "),"High: 3 Medium: 1 Low: 0") -> High: 3 Medium: 1 Low: 0
A8: =IFERROR(__xludf.DUMMYFUNCTION("""COMPUTED_VALUE"""),"Home") -> Home | B8: =IFERROR(__xludf.DUMMYFUNCTION("""COMPUTED_VALUE"""),"Home") -> Home | C8: =IFERROR(__xludf.DUMMYFUNCTION("TEXTJOIN("", "", TRUE, FILTER('Main Report'!A17:A106, ('Main Report'!B17:B106=A8) * ('Main Report'!C17:C106=B8) ) ) "),"BR-017, BR-018, BR-019") -> BR-017, BR-018, BR-019 | D8: =IFERROR(__xludf.DUMMYFUNCTION("COUNTA(UNIQUE(TRANSPOSE(SPLIT(C8, "", "")))) "),3.0) -> 3 | E8: =IF(D8="", "", TEXT((D8 / 'Main Report'!$E$7), "0.00%")) -> 7.50% | F8: =IFERROR(__xludf.DUMMYFUNCTION("IF(C8="""", """", TEXTJOIN("", "", TRUE, ""High: "" & COUNTIF(FILTER('Main Report'!K17:K106, ISNUMBER(MATCH('Main Report'!A17:A106, SPLIT(C8, "", ""), 0))), ""High"") & CHAR(10) & ""Medium: "" & COUNTIF(FILTER('Main Report'!K17:K106, ISNU"&"MBER(MATCH('Main Report'!A17:A106, SPLIT(C8, "", ""), 0))), ""Medium"") & CHAR(10) & ""Low: "" & COUNTIF(FILTER('Main Report'!K17:K106, ISNUMBER(MATCH('Main Report'!A17:A106, SPLIT(C8, "", ""), 0))), ""Low"") ) ) "),"High: 2 Medium: 1 Low: 0") -> High: 2 Medium: 1 Low: 0
A9: =IFERROR(__xludf.DUMMYFUNCTION("""COMPUTED_VALUE"""),"Home") -> Home | B9: =IFERROR(__xludf.DUMMYFUNCTION("""COMPUTED_VALUE"""),"Settings") -> Settings | C9: =IFERROR(__xludf.DUMMYFUNCTION("TEXTJOIN("", "", TRUE, FILTER('Main Report'!A18:A107, ('Main Report'!B18:B107=A9) * ('Main Report'!C18:C107=B9) ) ) "),"BR-020") -> BR-020 | D9: =IFERROR(__xludf.DUMMYFUNCTION("COUNTA(UNIQUE(TRANSPOSE(SPLIT(C9, "", "")))) "),1.0) -> 1 | E9: =IF(D9="", "", TEXT((D9 / 'Main Report'!$E$7), "0.00%")) -> 2.50% | F9: =IFERROR(__xludf.DUMMYFUNCTION("IF(C9="""", """", TEXTJOIN("", "", TRUE, ""High: "" & COUNTIF(FILTER('Main Report'!K18:K107, ISNUMBER(MATCH('Main Report'!A18:A107, SPLIT(C9, "", ""), 0))), ""High"") & CHAR(10) & ""Medium: "" & COUNTIF(FILTER('Main Report'!K18:K107, ISNU"&"MBER(MATCH('Main Report'!A18:A107, SPLIT(C9, "", ""), 0))), ""Medium"") & CHAR(10) & ""Low: "" & COUNTIF(FILTER('Main Report'!K18:K107, ISNUMBER(MATCH('Main Report'!A18:A107, SPLIT(C9, "", ""), 0))), ""Low"") ) ) "),"High: 0 Medium: 1 Low: 0") -> High: 0 Medium: 1 Low: 0
A10: =IFERROR(__xludf.DUMMYFUNCTION("""COMPUTED_VALUE"""),"Login") -> Login | B10: =IFERROR(__xludf.DUMMYFUNCTION("""COMPUTED_VALUE"""),"Forget Password") -> Forget Password | C10: =IFERROR(__xludf.DUMMYFUNCTION("TEXTJOIN("", "", TRUE, FILTER('Main Report'!A19:A108, ('Main Report'!B19:B108=A10) * ('Main Report'!C19:C108=B10) ) ) "),"BR-021") -> BR-021 | D10: =IFERROR(__xludf.DUMMYFUNCTION("COUNTA(UNIQUE(TRANSPOSE(SPLIT(C10, "", "")))) "),1.0) -> 1 | E10: =IF(D10="", "", TEXT((D10 / 'Main Report'!$E$7), "0.00%")) -> 2.50% | F10: =IFERROR(__xludf.DUMMYFUNCTION("IF(C10="""", """", TEXTJOIN("", "", TRUE, ""High: "" & COUNTIF(FILTER('Main Report'!K19:K108, ISNUMBER(MATCH('Main Report'!A19:A108, SPLIT(C10, "", ""), 0))), ""High"") & CHAR(10) & ""Medium: "" & COUNTIF(FILTER('Main Report'!K19:K108, IS"&"NUMBER(MATCH('Main Report'!A19:A108, SPLIT(C10, "", ""), 0))), ""Medium"") & CHAR(10) & ""Low: "" & COUNTIF(FILTER('Main Report'!K19:K108, ISNUMBER(MATCH('Main Report'!A19:A108, SPLIT(C10, "", ""), 0))), ""Low"") ) ) "),"High: 1 Medium: 0 Low: 0") -> High: 1 Medium: 0 Low: 0
A11: =IFERROR(__xludf.DUMMYFUNCTION("""COMPUTED_VALUE"""),"Onboarding") -> Onboarding | B11: =IFERROR(__xludf.DUMMYFUNCTION("""COMPUTED_VALUE"""),"Onboarding") -> Onboarding | C11: =IFERROR(__xludf.DUMMYFUNCTION("TEXTJOIN("", "", TRUE, FILTER('Main Report'!A20:A109, ('Main Report'!B20:B109=A11) * ('Main Report'!C20:C109=B11) ) ) "),"BR-022") -> BR-022 | D11: =IFERROR(__xludf.DUMMYFUNCTION("COUNTA(UNIQUE(TRANSPOSE(SPLIT(C11, "", "")))) "),1.0) -> 1 | E11: =IF(D11="", "", TEXT((D11 / 'Main Report'!$E$7), "0.00%")) -> 2.50% | F11: =IFERROR(__xludf.DUMMYFUNCTION("IF(C11="""", """", TEXTJOIN("", "", TRUE, ""High: "" & COUNTIF(FILTER('Main Report'!K20:K109, ISNUMBER(MATCH('Main Report'!A20:A109, SPLIT(C11, "", ""), 0))), ""High"") & CHAR(10) & ""Medium: "" & COUNTIF(FILTER('Main Report'!K20:K109, IS"&"NUMBER(MATCH('Main Report'!A20:A109, SPLIT(C11, "", ""), 0))), ""Medium"") & CHAR(10) & ""Low: "" & COUNTIF(FILTER('Main Report'!K20:K109, ISNUMBER(MATCH('Main Report'!A20:A109, SPLIT(C11, "", ""), 0))), ""Low"") ) ) "),"High: 1 Medium: 0 Low: 0") -> High: 1 Medium: 0 Low: 0
A12: =IFERROR(__xludf.DUMMYFUNCTION("""COMPUTED_VALUE"""),"Settings") -> Settings | B12: =IFERROR(__xludf.DUMMYFUNCTION("""COMPUTED_VALUE"""),"Help and Support") -> Help and Support | C12: =IFERROR(__xludf.DUMMYFUNCTION("TEXTJOIN("", "", TRUE, FILTER('Main Report'!A21:A110, ('Main Report'!B21:B110=A12) * ('Main Report'!C21:C110=B12) ) ) "),"BR-023, BR-024, BR-025") -> BR-023, BR-024, BR-025 | D12: =IFERROR(__xludf.DUMMYFUNCTION("COUNTA(UNIQUE(TRANSPOSE(SPLIT(C12, "", "")))) "),3.0) -> 3 | E12: =IF(D12="", "", TEXT((D12 / 'Main Report'!$E$7), "0.00%")) -> 7.50% | F12: =IFERROR(__xludf.DUMMYFUNCTION("IF(C12="""", """", TEXTJOIN("", "", TRUE, ""High: "" & COUNTIF(FILTER('Main Report'!K21:K110, ISNUMBER(MATCH('Main Report'!A21:A110, SPLIT(C12, "", ""), 0))), ""High"") & CHAR(10) & ""Medium: "" & COUNTIF(FILTER('Main Report'!K21:K110, IS"&"NUMBER(MATCH('Main Report'!A21:A110, SPLIT(C12, "", ""), 0))), ""Medium"") & CHAR(10) & ""Low: "" & COUNTIF(FILTER('Main Report'!K21:K110, ISNUMBER(MATCH('Main Report'!A21:A110, SPLIT(C12, "", ""), 0))), ""Low"") ) ) "),"High: 3 Medium: 0 Low: 0") -> High: 3 Medium: 0 Low: 0
A13: =IFERROR(__xludf.DUMMYFUNCTION("""COMPUTED_VALUE"""),"Settings") -> Settings | B13: =IFERROR(__xludf.DUMMYFUNCTION("""COMPUTED_VALUE"""),"Profile Information") -> Profile Information | C13: =IFERROR(__xludf.DUMMYFUNCTION("TEXTJOIN("", "", TRUE, FILTER('Main Report'!A22:A111, ('Main Report'!B22:B111=A13) * ('Main Report'!C22:C111=B13) ) ) "),"BR-026, BR-027, BR-028") -> BR-026, BR-027, BR-028 | D13: =IFERROR(__xludf.DUMMYFUNCTION("COUNTA(UNIQUE(TRANSPOSE(SPLIT(C13, "", "")))) "),3.0) -> 3 | E13: =IF(D13="", "", TEXT((D13 / 'Main Report'!$E$7), "0.00%")) -> 7.50% | F13: =IFERROR(__xludf.DUMMYFUNCTION("IF(C13="""", """", TEXTJOIN("", "", TRUE, ""High: "" & COUNTIF(FILTER('Main Report'!K22:K111, ISNUMBER(MATCH('Main Report'!A22:A111, SPLIT(C13, "", ""), 0))), ""High"") & CHAR(10) & ""Medium: "" & COUNTIF(FILTER('Main Report'!K22:K111, IS"&"NUMBER(MATCH('Main Report'!A22:A111, SPLIT(C13, "", ""), 0))), ""Medium"") & CHAR(10) & ""Low: "" & COUNTIF(FILTER('Main Report'!K22:K111, ISNUMBER(MATCH('Main Report'!A22:A111, SPLIT(C13, "", ""), 0))), ""Low"") ) ) "),"High: 2 Medium: 1 Low: 0") -> High: 2 Medium: 1 Low: 0
A14: =IFERROR(__xludf.DUMMYFUNCTION("""COMPUTED_VALUE"""),"Signup") -> Signup | B14: =IFERROR(__xludf.DUMMYFUNCTION("""COMPUTED_VALUE"""),"OTP") -> OTP | C14: =IFERROR(__xludf.DUMMYFUNCTION("TEXTJOIN("", "", TRUE, FILTER('Main Report'!A23:A112, ('Main Report'!B23:B112=A14) * ('Main Report'!C23:C112=B14) ) ) "),"BR-029") -> BR-029 | D14: =IFERROR(__xludf.DUMMYFUNCTION("COUNTA(UNIQUE(TRANSPOSE(SPLIT(C14, "", "")))) "),1.0) -> 1 | E14: =IF(D14="", "", TEXT((D14 / 'Main Report'!$E$7), "0.00%")) -> 2.50% | F14: =IFERROR(__xludf.DUMMYFUNCTION("IF(C14="""", """", TEXTJOIN("", "", TRUE, ""High: "" & COUNTIF(FILTER('Main Report'!K23:K112, ISNUMBER(MATCH('Main Report'!A23:A112, SPLIT(C14, "", ""), 0))), ""High"") & CHAR(10) & ""Medium: "" & COUNTIF(FILTER('Main Report'!K23:K112, IS"&"NUMBER(MATCH('Main Report'!A23:A112, SPLIT(C14, "", ""), 0))), ""Medium"") & CHAR(10) & ""Low: "" & COUNTIF(FILTER('Main Report'!K23:K112, ISNUMBER(MATCH('Main Report'!A23:A112, SPLIT(C14, "", ""), 0))), ""Low"") ) ) "),"High: 1 Medium: 0 Low: 0") -> High: 1 Medium: 0 Low: 0
A15: =IFERROR(__xludf.DUMMYFUNCTION("""COMPUTED_VALUE"""),"Signup") -> Signup | B15: =IFERROR(__xludf.DUMMYFUNCTION("""COMPUTED_VALUE"""),"Signup") -> Signup | C15: =IFERROR(__xludf.DUMMYFUNCTION("TEXTJOIN("", "", TRUE, FILTER('Main Report'!A24:A113, ('Main Report'!B24:B113=A15) * ('Main Report'!C24:C113=B15) ) ) "),"BR-030, BR-031") -> BR-030, BR-031 | D15: =IFERROR(__xludf.DUMMYFUNCTION("COUNTA(UNIQUE(TRANSPOSE(SPLIT(C15, "", "")))) "),2.0) -> 2 | E15: =IF(D15="", "", TEXT((D15 / 'Main Report'!$E$7), "0.00%")) -> 5.00% | F15: =IFERROR(__xludf.DUMMYFUNCTION("IF(C15="""", """", TEXTJOIN("", "", TRUE, ""High: "" & COUNTIF(FILTER('Main Report'!K24:K113, ISNUMBER(MATCH('Main Report'!A24:A113, SPLIT(C15, "", ""), 0))), ""High"") & CHAR(10) & ""Medium: "" & COUNTIF(FILTER('Main Report'!K24:K113, IS"&"NUMBER(MATCH('Main Report'!A24:A113, SPLIT(C15, "", ""), 0))), ""Medium"") & CHAR(10) & ""Low: "" & COUNTIF(FILTER('Main Report'!K24:K113, ISNUMBER(MATCH('Main Report'!A24:A113, SPLIT(C15, "", ""), 0))), ""Low"") ) ) "),"High: 1 Medium: 0 Low: 1") -> High: 1 Medium: 0 Low: 1
A16: =IFERROR(__xludf.DUMMYFUNCTION("""COMPUTED_VALUE"""),"Splash Screen") -> Splash Screen | B16: =IFERROR(__xludf.DUMMYFUNCTION("""COMPUTED_VALUE"""),"Splash Screen") -> Splash Screen | C16: =IFERROR(__xludf.DUMMYFUNCTION("TEXTJOIN("", "", TRUE, FILTER('Main Report'!A25:A114, ('Main Report'!B25:B114=A16) * ('Main Report'!C25:C114=B16) ) ) "),"BR-032, BR-033") -> BR-032, BR-033 | D16: =IFERROR(__xludf.DUMMYFUNCTION("COUNTA(UNIQUE(TRANSPOSE(SPLIT(C16, "", "")))) "),2.0) -> 2 | E16: =IF(D16="", "", TEXT((D16 / 'Main Report'!$E$7), "0.00%")) -> 5.00% | F16: =IFERROR(__xludf.DUMMYFUNCTION("IF(C16="""", """", TEXTJOIN("", "", TRUE, ""High: "" & COUNTIF(FILTER('Main Report'!K25:K114, ISNUMBER(MATCH('Main Report'!A25:A114, SPLIT(C16, "", ""), 0))), ""High"") & CHAR(10) & ""Medium: "" & COUNTIF(FILTER('Main Report'!K25:K114, IS"&"NUMBER(MATCH('Main Report'!A25:A114, SPLIT(C16, "", ""), 0))), ""Medium"") & CHAR(10) & ""Low: "" & COUNTIF(FILTER('Main Report'!K25:K114, ISNUMBER(MATCH('Main Report'!A25:A114, SPLIT(C16, "", ""), 0))), ""Low"") ) ) "),"High: 0 Medium: 2 Low: 0") -> High: 0 Medium: 2 Low: 0
A17: =IFERROR(__xludf.DUMMYFUNCTION("""COMPUTED_VALUE"""),"Subscription") -> Subscription | B17: =IFERROR(__xludf.DUMMYFUNCTION("""COMPUTED_VALUE"""),"Subscription") -> Subscription | C17: =IFERROR(__xludf.DUMMYFUNCTION("TEXTJOIN("", "", TRUE, FILTER('Main Report'!A26:A115, ('Main Report'!B26:B115=A17) * ('Main Report'!C26:C115=B17) ) ) "),"BR-034, BR-035, BR-036, BR-037, BR-038, BR-039, BR-040") -> BR-034, BR-035, BR-036, BR-037, BR-038, BR-039, BR-040 | E17: =IF(D17="", "", TEXT((D17 / 'Main Report'!$E$7), "0.00%")) | F17: =IFERROR(__xludf.DUMMYFUNCTION("IF(C17="""", """", TEXTJOIN("", "", TRUE, ""High: "" & COUNTIF(FILTER('Main Report'!K26:K115, ISNUMBER(MATCH('Main Report'!A26:A115, SPLIT(C17, "", ""), 0))), ""High"") & CHAR(10) & ""Medium: "" & COUNTIF(FILTER('Main Report'!K26:K115, IS"&"NUMBER(MATCH('Main Report'!A26:A115, SPLIT(C17, "", ""), 0))), ""Medium"") & CHAR(10) & ""Low: "" & COUNTIF(FILTER('Main Report'!K26:K115, ISNUMBER(MATCH('Main Report'!A26:A115, SPLIT(C17, "", ""), 0))), ""Low"") ) ) "),"High: 6 Medium: 1 Low: 0") -> High: 6 Medium: 1 Low: 0
C18: =IFERROR(__xludf.DUMMYFUNCTION("TEXTJOIN("", "", TRUE, FILTER('Main Report'!A27:A116, ('Main Report'!B27:B116=A18) * ('Main Report'!C27:C116=B18) ) ) "),"") | E18: =IF(D18="", "", TEXT((D18 / 'Main Report'!$E$7), "0.00%")) | F18: =IFERROR(__xludf.DUMMYFUNCTION("IF(C18="""", """", TEXTJOIN("", "", TRUE, ""High: "" & COUNTIF(FILTER('Main Report'!K27:K116, ISNUMBER(MATCH('Main Report'!A27:A116, SPLIT(C18, "", ""), 0))), ""High"") & CHAR(10) & ""Medium: "" & COUNTIF(FILTER('Main Report'!K27:K116, IS"&"NUMBER(MATCH('Main Report'!A27:A116, SPLIT(C18, "", ""), 0))), ""Medium"") & CHAR(10) & ""Low: "" & COUNTIF(FILTER('Main Report'!K27:K116, ISNUMBER(MATCH('Main Report'!A27:A116, SPLIT(C18, "", ""), 0))), ""Low"") ) ) "),"")
C19: =IFERROR(__xludf.DUMMYFUNCTION("TEXTJOIN("", "", TRUE, FILTER('Main Report'!A28:A117, ('Main Report'!B28:B117=A19) * ('Main Report'!C28:C117=B19) ) ) "),"") | E19: =IF(D19="", "", TEXT((D19 / 'Main Report'!$E$7), "0.00%")) | F19: =IFERROR(__xludf.DUMMYFUNCTION("IF(C19="""", """", TEXTJOIN("", "", TRUE, ""High: "" & COUNTIF(FILTER('Main Report'!K28:K117, ISNUMBER(MATCH('Main Report'!A28:A117, SPLIT(C19, "", ""), 0))), ""High"") & CHAR(10) & ""Medium: "" & COUNTIF(FILTER('Main Report'!K28:K117, IS"&"NUMBER(MATCH('Main Report'!A28:A117, SPLIT(C19, "", ""), 0))), ""Medium"") & CHAR(10) & ""Low: "" & COUNTIF(FILTER('Main Report'!K28:K117, ISNUMBER(MATCH('Main Report'!A28:A117, SPLIT(C19, "", ""), 0))), ""Low"") ) ) "),"")
C20: =IFERROR(__xludf.DUMMYFUNCTION("TEXTJOIN("", "", TRUE, FILTER('Main Report'!A29:A118, ('Main Report'!B29:B118=A20) * ('Main Report'!C29:C118=B20) ) ) "),"") | E20: =IF(D20="", "", TEXT((D20 / 'Main Report'!$E$7), "0.00%")) | F20: =IFERROR(__xludf.DUMMYFUNCTION("IF(C20="""", """", TEXTJOIN("", "", TRUE, ""High: "" & COUNTIF(FILTER('Main Report'!K29:K118, ISNUMBER(MATCH('Main Report'!A29:A118, SPLIT(C20, "", ""), 0))), ""High"") & CHAR(10) & ""Medium: "" & COUNTIF(FILTER('Main Report'!K29:K118, IS"&"NUMBER(MATCH('Main Report'!A29:A118, SPLIT(C20, "", ""), 0))), ""Medium"") & CHAR(10) & ""Low: "" & COUNTIF(FILTER('Main Report'!K29:K118, ISNUMBER(MATCH('Main Report'!A29:A118, SPLIT(C20, "", ""), 0))), ""Low"") ) ) "),"")
C21: =IFERROR(__xludf.DUMMYFUNCTION("TEXTJOIN("", "", TRUE, FILTER('Main Report'!A30:A119, ('Main Report'!B30:B119=A21) * ('Main Report'!C30:C119=B21) ) ) "),"") | E21: =IF(D21="", "", TEXT((D21 / 'Main Report'!$E$7), "0.00%")) | F21: =IFERROR(__xludf.DUMMYFUNCTION("IF(C21="""", """", TEXTJOIN("", "", TRUE, ""High: "" & COUNTIF(FILTER('Main Report'!K30:K119, ISNUMBER(MATCH('Main Report'!A30:A119, SPLIT(C21, "", ""), 0))), ""High"") & CHAR(10) & ""Medium: "" & COUNTIF(FILTER('Main Report'!K30:K119, IS"&"NUMBER(MATCH('Main Report'!A30:A119, SPLIT(C21, "", ""), 0))), ""Medium"") & CHAR(10) & ""Low: "" & COUNTIF(FILTER('Main Report'!K30:K119, ISNUMBER(MATCH('Main Report'!A30:A119, SPLIT(C21, "", ""), 0))), ""Low"") ) ) "),"")

Sheet Main Report
A2: Tester : | B2: Mohammed Fahad Faisal | D2: Severity | E2: Issues
A3: Project Name: | D3: High | E3: =COUNTIF(Tahsin!K14:K897, "High") + COUNTIF(Fahad!K8:K1004, "High") -> 26
A4: Project URL: | D4: Medium | E4: =COUNTIF(Tahsin!K14:K898, "Medium") + COUNTIF(Fahad!K8:K1005, "Medium") -> 12
A5: Developer: | D5: Low | E5: =COUNTIF(Fahad!K8:K1006, "Low") + COUNTIF(Tahsin!K14:K901, "Low") -> 2
A6: OS:
A7: Environment | D7: Total Test Cases: | E7: =SUM(E3:E5) -> 40 | N7: Place solve if the issue resolves | \/ | O7: Mention which Stack solved the issue | \/
D8: Test Case Solved : | E8: =COUNTIF(N11:N2387, "Solved") -> 29
A10: Test Case ID | B10: Module | C10: Sub Module | D10: Test Case Description | E10: Preconditions | F10: Test Steps | G10: Test Data | H10: Expected Result | I10: Actual Result | J10: Status | K10: Severity | L10: Screen Shots | M10: Suggestion | N10: Feedback | O10: Stack | P10: Comment | Q10: Tester
A11: {=IF((LEN(B11:B100)+LEN(C11:C100))>0, "BR-" & TEXT(ROW(B11:B100)-ROW(B11)+1,"000"), "")} -> BR-001 | B11: =IFERROR(__xludf.DUMMYFUNCTION("QUERY( { ARRAYFORMULA({ TRIM(Fahad!B8:B2383), Fahad!C8:P2383, IF(LEN(Fahad!B8:B2383), ""Fahad"", """") }); ARRAYFORMULA({ TRIM(Tahsin!B15:B2383), Tahsin!C15:P2383, IF(LEN(Tahsin!B15:B2383), ""Tahsin"","&" """") }) }, ""SELECT * WHERE Col1 IS NOT NULL ORDER BY Col1 ASC, Col2 ASC"", 0 )"),"Basic Info") -> Basic Info | C11: =IFERROR(__xludf.DUMMYFUNCTION("""COMPUTED_VALUE"""),"Basic Info") -> Basic Info | D11: =IFERROR(__xludf.DUMMYFUNCTION("""COMPUTED_VALUE"""),"The required mark on basic information should be displayed correctly.") -> The required mark on basic information should be displayed correctly. | E11: =IFERROR(__xludf.DUMMYFUNCTION("""COMPUTED_VALUE"""),"User need to able to access website using browser") -> User need to able to access website using browser | F11: =IFERROR(__xludf.DUMMYFUNCTION("""COMPUTED_VALUE"""),"1. Open website of ParentBridge 2. Goto Login Page 3. Login using valid credentials") -> 1. Open website of ParentBridge 2. Goto Login Page 3. Login using valid credentials | G11: =IFERROR(__xludf.DUMMYFUNCTION("""COMPUTED_VALUE"""),"USER CREDENTIAL") -> USER CREDENTIAL | H11: =IFERROR(__xludf.DUMMYFUNCTION("""COMPUTED_VALUE"""),"A required mark should be placed in the input field.") -> A required mark should be placed in the input field. | I11: =IFERROR(__xludf.DUMMYFUNCTION("""COMPUTED_VALUE"""),"Required field are not mentioned.") -> Required field are not mentioned. | J11: =IFERROR(__xludf.DUMMYFUNCTION("""COMPUTED_VALUE"""),"Fail") -> Fail | K11: =IFERROR(__xludf.DUMMYFUNCTION("""COMPUTED_VALUE"""),"Medium") -> Medium | L11: =IFERROR(__xludf.DUMMYFUNCTION("""COMPUTED_VALUE"""),"007.png") -> 007.png | N11: =IFERROR(__xludf.DUMMYFUNCTION("""COMPUTED_VALUE"""),"Solved") -> Solved | O11: =IFERROR(__xludf.DUMMYFUNCTION("""COMPUTED_VALUE"""),"Front-End") -> Front-End | Q11: =IFERROR(__xludf.DUMMYFUNCTION("""COMPUTED_VALUE"""),"Fahad") -> Fahad
A12: BR-002 | B12: =IFERROR(__xludf.DUMMYFUNCTION("""COMPUTED_VALUE"""),"Basic Info") -> Basic Info | C12: =IFERROR(__xludf.DUMMYFUNCTION("""COMPUTED_VALUE"""),"Basic Info") -> Basic Info | D12: =IFERROR(__xludf.DUMMYFUNCTION("""COMPUTED_VALUE"""),"Character limit hasn’t been implemented.") -> Character limit hasn’t been implemented. | E12: =IFERROR(__xludf.DUMMYFUNCTION("""COMPUTED_VALUE"""),"User need to able to access website using browser") -> User need to able to access website using browser | F12: =IFERROR(__xludf.DUMMYFUNCTION("""COMPUTED_VALUE"""),"1. Open website of ParentBridge 2. Goto Login Page 3. Login using valid credentials") -> 1. Open website of ParentBridge 2. Goto Login Page 3. Login using valid credentials | G12: =IFERROR(__xludf.DUMMYFUNCTION("""COMPUTED_VALUE"""),"USER CREDENTIAL") -> USER CREDENTIAL | H12: =IFERROR(__xludf.DUMMYFUNCTION("""COMPUTED_VALUE"""),"The input field should allow users to enter only a limited number of characters.") -> The input field should allow users to enter only a limited number of characters. | I12: =IFERROR(__xludf.DUMMYFUNCTION("""COMPUTED_VALUE"""),"Can enter an unlimited number of characters in the input field.") -> Can enter an unlimited number of characters in the input field. | J12: =IFERROR(__xludf.DUMMYFUNCTION("""COMPUTED_VALUE"""),"Fail") -> Fail | K12: =IFERROR(__xludf.DUMMYFUNCTION("""COMPUTED_VALUE"""),"Low") -> Low | L12: =IFERROR(__xludf.DUMMYFUNCTION("""COMPUTED_VALUE"""),"008.png") -> 008.png | N12: =IFERROR(__xludf.DUMMYFUNCTION("""COMPUTED_VALUE"""),"Solved") -> Solved | O12: =IFERROR(__xludf.DUMMYFUNCTION("""COMPUTED_VALUE"""),"Front-End") -> Front-End | Q12: =IFERROR(__xludf.DUMMYFUNCTION("""COMPUTED_VALUE"""),"Fahad") -> Fahad
A13: BR-003 | B13: =IFERROR(__xludf.DUMMYFUNCTION("""COMPUTED_VALUE"""),"Basic Info") -> Basic Info | C13: =IFERROR(__xludf.DUMMYFUNCTION("""COMPUTED_VALUE"""),"Basic Info") -> Basic Info | D13: =IFERROR(__xludf.DUMMYFUNCTION("""COMPUTED_VALUE"""),"Data validation problem in the basic information.") -> Data validation problem in the basic information. | E13: =IFERROR(__xludf.DUMMYFUNCTION("""COMPUTED_VALUE"""),"User need to able to access website using browser") -> User need to able to access website using browser | F13: =IFERROR(__xludf.DUMMYFUNCTION("""COMPUTED_VALUE"""),"1. Open website of ParentBridge 2. Goto Login Page 3. Login using valid credentials") -> 1. Open website of ParentBridge 2. Goto Login Page 3. Login using valid credentials | G13: =IFERROR(__xludf.DUMMYFUNCTION("""COMPUTED_VALUE"""),"USER CREDENTIAL") -> USER CREDENTIAL | H13: =IFERROR(__xludf.DUMMYFUNCTION("""COMPUTED_VALUE"""),"Character field should only accept letters, while the number field should only accept numeric values.") -> Character field should only accept letters, while the number field should only accept numeric values. | I13: =IFERROR(__xludf.DUMMYFUNCTION("""COMPUTED_VALUE"""),"Data input validation hasn’t been implemented.") -> Data input validation hasn’t been implemented. | J13: =IFERROR(__xludf.DUMMYFUNCTION("""COMPUTED_VALUE"""),"Fail") -> Fail | K13: =IFERROR(__xludf.DUMMYFUNCTION("""COMPUTED_VALUE"""),"High") -> High | L13: =IFERROR(__xludf.DUMMYFUNCTION("""COMPUTED_VALUE"""),"009.png") -> 009.png | N13: =IFERROR(__xludf.DUMMYFUNCTION("""COMPUTED_VALUE"""),"Solved") -> Solved | O13: =IFERROR(__xludf.DUMMYFUNCTION("""COMPUTED_VALUE"""),"Front-End") -> Front-End | Q13: =IFERROR(__xludf.DUMMYFUNCTION("""COMPUTED_VALUE"""),"Fahad") -> Fahad
A14: BR-004 | B14: =IFERROR(__xludf.DUMMYFUNCTION("""COMPUTED_VALUE"""),"Home") -> Home | C14: =IFERROR(__xludf.DUMMYFUNCTION("""COMPUTED_VALUE"""),"Calendar") -> Calendar | D14: =IFERROR(__xludf.DUMMYFUNCTION("""COMPUTED_VALUE"""),"Children are given default names whenever a different name is entered.") -> Children are given default names whenever a different name is entered. | E14: =IFERROR(__xludf.DUMMYFUNCTION("""COMPUTED_VALUE"""),"User need to able to access website using browser") -> User need to able to access website using browser | F14: =IFERROR(__xludf.DUMMYFUNCTION("""COMPUTED_VALUE"""),"1. Open website of ParentBridge 2. Login using valid credential 3. goto Home 4. Click on calender") -> 1. Open website of ParentBridge 2. Login using valid credential 3. goto Home 4. Click on calender | G14: =IFERROR(__xludf.DUMMYFUNCTION("""COMPUTED_VALUE"""),"USER CREDENTIAL") -> USER CREDENTIAL | H14: =IFERROR(__xludf.DUMMYFUNCTION("""COMPUTED_VALUE"""),"Should display the child's name that is entered.") -> Should display the child's name that is entered. | I14: =IFERROR(__xludf.DUMMYFUNCTION("""COMPUTED_VALUE"""),"Default child names are showing up even when they haven’t been entered.") -> Default child names are showing up even when they haven’t been entered. | J14: =IFERROR(__xludf.DUMMYFUNCTION("""COMPUTED_VALUE"""),"Fail") -> Fail | K14: =IFERROR(__xludf.DUMMYFUNCTION("""COMPUTED_VALUE"""),"Medium") -> Medium | L14: =IFERROR(__xludf.DUMMYFUNCTION("""COMPUTED_VALUE"""),"018.png") -> 018.png | N14: =IFERROR(__xludf.DUMMYFUNCTION("""COMPUTED_VALUE"""),"Solved") -> Solved | O14: =IFERROR(__xludf.DUMMYFUNCTION("""COMPUTED_VALUE"""),"Front-End, Back-End") -> Front-End, Back-End | Q14: =IFERROR(__xludf.DUMMYFUNCTION("""COMPUTED_VALUE"""),"Fahad") -> Fahad
A15: BR-005 | B15: =IFERROR(__xludf.DUMMYFUNCTION("""COMPUTED_VALUE"""),"Home") -> Home | C15: =IFERROR(__xludf.DUMMYFUNCTION("""COMPUTED_VALUE"""),"Calendar") -> Calendar | D15: =IFERROR(__xludf.DUMMYFUNCTION("""COMPUTED_VALUE"""),"Can set an event in the past.") -> Can set an event in the past. | E15: =IFERROR(__xludf.DUMMYFUNCTION("""COMPUTED_VALUE"""),"User need to able to access website using browser") -> User need to able to access website using browser | F15: =IFERROR(__xludf.DUMMYFUNCTION("""COMPUTED_VALUE"""),"1. Open website of ParentBridge 2. Login using valid credential 3. goto Home 4. Click on calender") -> 1. Open website of ParentBridge 2. Login using valid credential 3. goto Home 4. Click on calender | G15: =IFERROR(__xludf.DUMMYFUNCTION("""COMPUTED_VALUE"""),"USER CREDENTIAL") -> USER CREDENTIAL | H15: =IFERROR(__xludf.DUMMYFUNCTION("""COMPUTED_VALUE"""),"Users shouldn’t be able to mark past events on the calendar to avoid any misunderstanding issues.") -> Users shouldn’t be able to mark past events on the calendar to avoid any misunderstanding issues. | I15: =IFERROR(__xludf.DUMMYFUNCTION("""COMPUTED_VALUE"""),"User is able to set mark on past event") -> User is able to set mark on past event | J15: =IFERROR(__xludf.DUMMYFUNCTION("""COMPUTED_VALUE"""),"Fail") -> Fail | K15: =IFERROR(__xludf.DUMMYFUNCTION("""COMPUTED_VALUE"""),"Medium") -> Medium | L15: =IFERROR(__xludf.DUMMYFUNCTION("""COMPUTED_VALUE"""),"019.png") -> 019.png | M15: =IFERROR(__xludf.DUMMYFUNCTION("""COMPUTED_VALUE"""),"Need to discuss this matter with client to avoid miss-understanding between co-parent ") -> Need to discuss this matter with client to avoid miss-understanding between co-parent | N15: =IFERROR(__xludf.DUMMYFUNCTION("""COMPUTED_VALUE"""),"Unsolved") -> Unsolved | O15: =IFERROR(__xludf.DUMMYFUNCTION("""COMPUTED_VALUE"""),"Back-End") -> Back-End | P15: =IFERROR(__xludf.DUMMYFUNCTION("""COMPUTED_VALUE"""),"If backend will fix this problem then in my frontend, it wont show the past event.") -> If backend will fix this problem then in my frontend, it wont show the past event. | Q15: =IFERROR(__xludf.DUMMYFUNCTION("""COMPUTED_VALUE"""),"Fahad") -> Fahad
A16: BR-006 | B16: =IFERROR(__xludf.DUMMYFUNCTION("""COMPUTED_VALUE"""),"Home") -> Home | C16: =IFERROR(__xludf.DUMMYFUNCTION("""COMPUTED_VALUE"""),"Calendar") -> Calendar | D16: =IFERROR(__xludf.DUMMYFUNCTION("""COMPUTED_VALUE"""),"Calendar navigation arrow missing in the frontend") -> Calendar navigation arrow missing in the frontend | E16: =IFERROR(__xludf.DUMMYFUNCTION("""COMPUTED_VALUE"""),"User need to able to access website using browser") -> User need to able to access website using browser | F16: =IFERROR(__xludf.DUMMYFUNCTION("""COMPUTED_VALUE"""),"1. Open website of ParentBridge 2. Login using valid credential 3. goto Home 4. Click on calender") -> 1. Open website of ParentBridge 2. Login using valid credential 3. goto Home 4. Click on calender | G16: =IFERROR(__xludf.DUMMYFUNCTION("""COMPUTED_VALUE"""),"USER CREDENTIAL") -> USER CREDENTIAL | H16: =IFERROR(__xludf.DUMMYFUNCTION("""COMPUTED_VALUE"""),"The calendar navigation arrow should be positioned to allow viewing of past events.") -> The calendar navigation arrow should be positioned to allow viewing of past events. | I16: =IFERROR(__xludf.DUMMYFUNCTION("""COMPUTED_VALUE"""),"Missing navigation arrow in calendar") -> Missing navigation arrow in calendar | J16: =IFERROR(__xludf.DUMMYFUNCTION("""COMPUTED_VALUE"""),"Fail") -> Fail | K16: =IFERROR(__xludf.DUMMYFUNCTION("""COMPUTED_VALUE"""),"Medium") -> Medium | L16: =IFERROR(__xludf.DUMMYFUNCTION("""COMPUTED_VALUE"""),"020.png") -> 020.png | N16: =IFERROR(__xludf.DUMMYFUNCTION("""COMPUTED_VALUE"""),"Solved") -> Solved | O16: =IFERROR(__xludf.DUMMYFUNCTION("""COMPUTED_VALUE"""),"Front-End") -> Front-End | Q16: =IFERROR(__xludf.DUMMYFUNCTION("""COMPUTED_VALUE"""),"Fahad") -> Fahad
A17: BR-007 | B17: =IFERROR(__xludf.DUMMYFUNCTION("""COMPUTED_VALUE"""),"Home") -> Home | C17: =IFERROR(__xludf.DUMMYFUNCTION("""COMPUTED_VALUE"""),"Calendar") -> Calendar | D17: =IFERROR(__xludf.DUMMYFUNCTION("""COMPUTED_VALUE"""),"Date wise event view failed") -> Date wise event view failed | E17: =IFERROR(__xludf.DUMMYFUNCTION("""COMPUTED_VALUE"""),"User need to able to access website using browser") -> User need to able to access website using browser | F17: =IFERROR(__xludf.DUMMYFUNCTION("""COMPUTED_VALUE"""),"1. Open website of ParentBridge 2. Login using valid credential 3. goto Home 4. Click on calender") -> 1. Open website of ParentBridge 2. Login using valid credential 3. goto Home 4. Click on calender | G17: =IFERROR(__xludf.DUMMYFUNCTION("""COMPUTED_VALUE"""),"USER CREDENTIAL") -> USER CREDENTIAL | H17: =IFERROR(__xludf.DUMMYFUNCTION("""COMPUTED_VALUE"""),"Event number under the date should be implemented according to the Figma requirements.") -> Event number under the date should be implemented according to the Figma requirements. | I17: =IFERROR(__xludf.DUMMYFUNCTION("""COMPUTED_VALUE"""),"Event number under the date is missing on the frontend.") -> Event number under the date is missing on the frontend. | J17: =IFERROR(__xludf.DUMMYFUNCTION("""COMPUTED_VALUE"""),"Fail") -> Fail | K17: =IFERROR(__xludf.DUMMYFUNCTION("""COMPUTED_VALUE"""),"High") -> High | L17: =IFERROR(__xludf.DUMMYFUNCTION("""COMPUTED_VALUE"""),"021.png") -> 021.png | N17: =IFERROR(__xludf.DUMMYFUNCTION("""COMPUTED_VALUE"""),"Solved") -> Solved | O17: =IFERROR(__xludf.DUMMYFUNCTION("""COMPUTED_VALUE"""),"Front-End") -> Front-End | Q17: =IFERROR(__xludf.DUMMYFUNCTION("""COMPUTED_VALUE"""),"Fahad") -> Fahad
A18: BR-008 | B18: =IFERROR(__xludf.DUMMYFUNCTION("""COMPUTED_VALUE"""),"Home") -> Home | C18: =IFERROR(__xludf.DUMMYFUNCTION("""COMPUTED_VALUE"""),"Calendar") -> Calendar | D18: =IFERROR(__xludf.DUMMYFUNCTION("""COMPUTED_VALUE"""),"Failed to add holiday planner to calendar.") -> Failed to add holiday planner to calendar. | E18: =IFERROR(__xludf.DUMMYFUNCTION("""COMPUTED_VALUE"""),"User need to able to access website using browser") -> User need to able to access website using browser | F18: =IFERROR(__xludf.DUMMYFUNCTION("""COMPUTED_VALUE"""),"1. Open website of ParentBridge 2. Login using valid credential 3. goto Home 4. Click on calender") -> 1. Open website of ParentBridge 2. Login using valid credential 3. goto Home 4. Click on calender | G18: =IFERROR(__xludf.DUMMYFUNCTION("""COMPUTED_VALUE"""),"USER CREDENTIAL") -> USER CREDENTIAL | H18: =IFERROR(__xludf.DUMMYFUNCTION("""COMPUTED_VALUE"""),"Users should be able to add a holiday planner to their calendar.") -> Users should be able to add a holiday planner to their calendar. | I18: =IFERROR(__xludf.DUMMYFUNCTION("""COMPUTED_VALUE"""),"Couldn’t add the holiday planner to the calendar section.") -> Couldn’t add the holiday planner to the calendar section. | J18: =IFERROR(__xludf.DUMMYFUNCTION("""COMPUTED_VALUE"""),"Fail") -> Fail | K18: =IFERROR(__xludf.DUMMYFUNCTION("""COMPUTED_VALUE"""),"High") -> High | L18: =IFERROR(__xludf.DUMMYFUNCTION("""COMPUTED_VALUE"""),"022.png") -> 022.png | N18: =IFERROR(__xludf.DUMMYFUNCTION("""COMPUTED_VALUE"""),"Solved") -> Solved | O18: =IFERROR(__xludf.DUMMYFUNCTION("""COMPUTED_VALUE"""),"Front-End") -> Front-End | Q18: =IFERROR(__xludf.DUMMYFUNCTION("""COMPUTED_VALUE"""),"Fahad") -> Fahad
A19: BR-009 | B19: =IFERROR(__xludf.DUMMYFUNCTION("""COMPUTED_VALUE"""),"Home") -> Home | C19: =IFERROR(__xludf.DUMMYFUNCTION("""COMPUTED_VALUE"""),"Calendar") -> Calendar | D19: =IFERROR(__xludf.DUMMYFUNCTION("""COMPUTED_VALUE"""),"All-day event toggle button is missing from the frontend.") -> All-day event toggle button is missing from the frontend. | E19: =IFERROR(__xludf.DUMMYFUNCTION("""COMPUTED_VALUE"""),"User need to able to access website using browser") -> User need to able to access website using browser | F19: =IFERROR(__xludf.DUMMYFUNCTION("""COMPUTED_VALUE"""),"1. Open website of ParentBridge 2. Login using valid credential 3. goto Home 4. Click on calender 5. Click on add event ") -> 1. Open website of ParentBridge 2. Login using valid credential 3. goto Home 4. Click on calender 5. Click on add event | G19: =IFERROR(__xludf.DUMMYFUNCTION("""COMPUTED_VALUE"""),"USER CREDENTIAL") -> USER CREDENTIAL | H19: =IFERROR(__xludf.DUMMYFUNCTION("""COMPUTED_VALUE"""),"Feature should be available as shown in Figma.") -> Feature should be available as shown in Figma. | I19: =IFERROR(__xludf.DUMMYFUNCTION("""COMPUTED_VALUE"""),"All-day event button is missing in the frontend") -> All-day event button is missing in the frontend | J19: =IFERROR(__xludf.DUMMYFUNCTION("""COMPUTED_VALUE"""),"Fail") -> Fail | K19: =IFERROR(__xludf.DUMMYFUNCTION("""COMPUTED_VALUE"""),"High") -> High | L19: =IFERROR(__xludf.DUMMYFUNCTION("""COMPUTED_VALUE"""),"024.png") -> 024.png | N19: =IFERROR(__xludf.DUMMYFUNCTION("""COMPUTED_VALUE"""),"Solved") -> Solved | O19: =IFERROR(__xludf.DUMMYFUNCTION("""COMPUTED_VALUE"""),"Front-End") -> Front-End | Q19: =IFERROR(__xludf.DUMMYFUNCTION("""COMPUTED_VALUE"""),"Fahad") -> Fahad
A20: BR-010 | B20: =IFERROR(__xludf.DUMMYFUNCTION("""COMPUTED_VALUE"""),"Home") -> Home | C20: =IFERROR(__xludf.DUMMYFUNCTION("""COMPUTED_VALUE"""),"Calls") -> Calls | D20: =IFERROR(__xludf.DUMMYFUNCTION("""COMPUTED_VALUE"""),"Unable to connect with co-parent") -> Unable to connect with co-parent | E20: =IFERROR(__xludf.DUMMYFUNCTION("""COMPUTED_VALUE"""),"User need to able to access website using browser") -> User need to able to access website using browser | F20: =IFERROR(__xludf.DUMMYFUNCTION("""COMPUTED_VALUE"""),"1. Open website of ParentBridge 2. Login using valid credential 3. goto Home 4. goto up comming events section") -> 1. Open website of ParentBridge 2. Login using valid credential 3. goto Home 4. goto up comming events section | G20: =IFERROR(__xludf.DUMMYFUNCTION("""COMPUTED_VALUE"""),"USER CREDENTIAL") -> USER CREDENTIAL | H20: =IFERROR(__xludf.DUMMYFUNCTION("""COMPUTED_VALUE"""),"Users should have the option to add co-parents right after creating an account or choose to add them later.") -> Users should have the option to add co-parents right after creating an account or choose to add them later. | I20: =IFERROR(__xludf.DUMMYFUNCTION("""COMPUTED_VALUE"""),"Couldn’t add a co-parent after setting up the account.") -> Couldn’t add a co-parent after setting up the account. | J20: =IFERROR(__xludf.DUMMYFUNCTION("""COMPUTED_VALUE"""),"Fail") -> Fail | K20: =IFERROR(__xludf.DUMMYFUNCTION("""COMPUTED_VALUE"""),"High") -> High | L20: =IFERROR(__xludf.DUMMYFUNCTION("""COMPUTED_VALUE"""),"017.png") -> 017.png | N20: =IFERROR(__xludf.DUMMYFUNCTION("""COMPUTED_VALUE"""),"Solved") -> Solved | O20: =IFERROR(__xludf.DUMMYFUNCTION("""COMPUTED_VALUE"""),"Front-End, Back-End") -> Front-End, Back-End | Q20: =IFERROR(__xludf.DUMMYFUNCTION("""COMPUTED_VALUE"""),"Fahad") -> Fahad
A21: BR-011 | B21: =IFERROR(__xludf.DUMMYFUNCTION("""COMPUTED_VALUE"""),"Home") -> Home | C21: =IFERROR(__xludf.DUMMYFUNCTION("""COMPUTED_VALUE"""),"Chat") -> Chat | D21: =IFERROR(__xludf.DUMMYFUNCTION("""COMPUTED_VALUE"""),"A non-functional button has been noticed.") -> A non-functional button has been noticed. | E21: =IFERROR(__xludf.DUMMYFUNCTION("""COMPUTED_VALUE"""),"User need to able to access website using browser") -> User need to able to access website using browser | F21: =IFERROR(__xludf.DUMMYFUNCTION("""COMPUTED_VALUE"""),"1. Open website of ParentBridge 2. Login using valid credential 3. goto chat") -> 1. Open website of ParentBridge 2. Login using valid credential 3. goto chat | G21: =IFERROR(__xludf.DUMMYFUNCTION("""COMPUTED_VALUE"""),"USER CREDENTIAL") -> USER CREDENTIAL | H21: =IFERROR(__xludf.DUMMYFUNCTION("""COMPUTED_VALUE"""),"The settings button and options should be accessible in the chat section.") -> The settings button and options should be accessible in the chat section. | I21: =IFERROR(__xludf.DUMMYFUNCTION("""COMPUTED_VALUE"""),"Chat options are missing in the frontend.") -> Chat options are missing in the frontend. | J21: =IFERROR(__xludf.DUMMYFUNCTION("""COMPUTED_VALUE"""),"Fail") -> Fail | K21: =IFERROR(__xludf.DUMMYFUNCTION("""COMPUTED_VALUE"""),"Medium") -> Medium | L21: =IFERROR(__xludf.DUMMYFUNCTION("""COMPUTED_VALUE"""),"014.png") -> 014.png | N21: =IFERROR(__xludf.DUMMYFUNCTION("""COMPUTED_VALUE"""),"Solved") -> Solved | O21: =IFERROR(__xludf.DUMMYFUNCTION("""COMPUTED_VALUE"""),"Front-End") -> Front-End | Q21: =IFERROR(__xludf.DUMMYFUNCTION("""COMPUTED_VALUE"""),"Fahad") -> Fahad
A22: BR-012 | B22: =IFERROR(__xludf.DUMMYFUNCTION("""COMPUTED_VALUE"""),"Home") -> Home | C22: =IFERROR(__xludf.DUMMYFUNCTION("""COMPUTED_VALUE"""),"Documents") -> Documents | D22: =IFERROR(__xludf.DUMMYFUNCTION("""COMPUTED_VALUE"""),"Can't upload document on the frontend.") -> Can't upload document on the frontend. | E22: =IFERROR(__xludf.DUMMYFUNCTION("""COMPUTED_VALUE"""),"User need to able to access website using browser") -> User need to able to access website using browser | F22: =IFERROR(__xludf.DUMMYFUNCTION("""COMPUTED_VALUE"""),"1. Open website of ParentBridge 2. Login using valid credential 3. goto Home 4. Click on calender") -> 1. Open website of ParentBridge 2. Login using valid credential 3. goto Home 4. Click on calender | G22: =IFERROR(__xludf.DUMMYFUNCTION("""COMPUTED_VALUE"""),"USER CREDENTIAL") -> USER CREDENTIAL | H22: =IFERROR(__xludf.DUMMYFUNCTION("""COMPUTED_VALUE"""),"User should be able to upload a document without any issues.") -> User should be able to upload a document without any issues. | I22: =IFERROR(__xludf.DUMMYFUNCTION("""COMPUTED_VALUE"""),"Unable to upload document.") -> Unable to upload document. | J22: =IFERROR(__xludf.DUMMYFUNCTION("""COMPUTED_VALUE"""),"Fail") -> Fail | K22: =IFERROR(__xludf.DUMMYFUNCTION("""COMPUTED_VALUE"""),"High") -> High | L22: =IFERROR(__xludf.DUMMYFUNCTION("""COMPUTED_VALUE"""),"023.png") -> 023.png | N22: =IFERROR(__xludf.DUMMYFUNCTION("""COMPUTED_VALUE"""),"Solved") -> Solved | O22: =IFERROR(__xludf.DUMMYFUNCTION("""COMPUTED_VALUE"""),"Front-End") -> Front-End | P22: =IFERROR(__xludf.DUMMYFUNCTION("""COMPUTED_VALUE"""),"The images and the pdf is not showing in the website because backend is using local base url") -> The images and the pdf is not showing in the website because backend is using local base url | Q22: =IFERROR(__xludf.DUMMYFUNCTION("""COMPUTED_VALUE"""),"Fahad") -> Fahad
A23: BR-013 | B23: =IFERROR(__xludf.DUMMYFUNCTION("""COMPUTED_VALUE"""),"Home") -> Home | C23: =IFERROR(__xludf.DUMMYFUNCTION("""COMPUTED_VALUE"""),"Expense") -> Expense | D23: =IFERROR(__xludf.DUMMYFUNCTION("""COMPUTED_VALUE"""),"Placeholder text color blends with the background, making it hard to read.") -> Placeholder text color blends with the background, making it hard to read. | E23: =IFERROR(__xludf.DUMMYFUNCTION("""COMPUTED_VALUE"""),"User need to able to access website using browser") -> User need to able to access website using browser | F23: =IFERROR(__xludf.DUMMYFUNCTION("""COMPUTED_VALUE"""),"1. Open website of ParentBridge 2. Login using valid credentials 3. click on expense") -> 1. Open website of ParentBridge 2. Login using valid credentials 3. click on expense | G23: =IFERROR(__xludf.DUMMYFUNCTION("""COMPUTED_VALUE"""),"USER CREDENTIAL") -> USER CREDENTIAL | H23: =IFERROR(__xludf.DUMMYFUNCTION("""COMPUTED_VALUE"""),"Placeholder text should be in the opposite color of the background for better visibility and user understanding.") -> Placeholder text should be in the opposite color of the background for better visibility and user understanding. | I23: =IFERROR(__xludf.DUMMYFUNCTION("""COMPUTED_VALUE"""),"Background color and the placeholder text color are the same, making it difficult to read the text.") -> Background color and the placeholder text color are the same, making it difficult to read the text. | J23: =IFERROR(__xludf.DUMMYFUNCTION("""COMPUTED_VALUE"""),"Fail") -> Fail | K23: =IFERROR(__xludf.DUMMYFUNCTION("""COMPUTED_VALUE"""),"Medium") -> Medium | L23: =IFERROR(__xludf.DUMMYFUNCTION("""COMPUTED_VALUE"""),"033.png") -> 033.png | N23: =IFERROR(__xludf.DUMMYFUNCTION("""COMPUTED_VALUE"""),"Solved") -> Solved | O23: =IFERROR(__xludf.DUMMYFUNCTION("""COMPUTED_VALUE"""),"Front-End") -> Front-End | Q23: =IFERROR(__xludf.DUMMYFUNCTION("""COMPUTED_VALUE"""),"Fahad") -> Fahad
A24: BR-014 | B24: =IFERROR(__xludf.DUMMYFUNCTION("""COMPUTED_VALUE"""),"Home") -> Home | C24: =IFERROR(__xludf.DUMMYFUNCTION("""COMPUTED_VALUE"""),"Expense") -> Expense | D24: =IFERROR(__xludf.DUMMYFUNCTION("""COMPUTED_VALUE"""),"Export feature hasn’t been added yet.") -> Export feature hasn’t been added yet. | E24: =IFERROR(__xludf.DUMMYFUNCTION("""COMPUTED_VALUE"""),"User need to able to access website using browser") -> User need to able to access website using browser | F24: =IFERROR(__xludf.DUMMYFUNCTION("""COMPUTED_VALUE"""),"1. Open website of ParentBridge 2. Login using valid credentials 3. click on expense") -> 1. Open website of ParentBridge 2. Login using valid credentials 3. click on expense | G24: =IFERROR(__xludf.DUMMYFUNCTION("""COMPUTED_VALUE"""),"USER CREDENTIAL") -> USER CREDENTIAL | H24: =IFERROR(__xludf.DUMMYFUNCTION("""COMPUTED_VALUE"""),"Export feature should be implemented according to the Figma design.") -> Export feature should be implemented according to the Figma design. | I24: =IFERROR(__xludf.DUMMYFUNCTION("""COMPUTED_VALUE"""),"Export feature is missing on the web.") -> Export feature is missing on the web. | J24: =IFERROR(__xludf.DUMMYFUNCTION("""COMPUTED_VALUE"""),"Fail") -> Fail | K24: =IFERROR(__xludf.DUMMYFUNCTION("""COMPUTED_VALUE"""),"High") -> High | L24: =IFERROR(__xludf.DUMMYFUNCTION("""COMPUTED_VALUE"""),"034.png") -> 034.png | N24: =IFERROR(__xludf.DUMMYFUNCTION("""COMPUTED_VALUE"""),"Unsolved") -> Unsolved | O24: =IFERROR(__xludf.DUMMYFUNCTION("""COMPUTED_VALUE"""),"Back-End") -> Back-End | P24: =IFERROR(__xludf.DUMMYFUNCTION("""COMPUTED_VALUE"""),"Export feature is not implmeneted in backend") -> Export feature is not implmeneted in backend | Q24: =IFERROR(__xludf.DUMMYFUNCTION("""COMPUTED_VALUE"""),"Fahad") -> Fahad
A25: BR-015 | B25: =IFERROR(__xludf.DUMMYFUNCTION("""COMPUTED_VALUE"""),"Home") -> Home | C25: =IFERROR(__xludf.DUMMYFUNCTION("""COMPUTED_VALUE"""),"Expense") -> Expense | D25: =IFERROR(__xludf.DUMMYFUNCTION("""COMPUTED_VALUE"""),"Parent and co-parent expenses are not displayed correctly.") -> Parent and co-parent expenses are not displayed correctly. | E25: =IFERROR(__xludf.DUMMYFUNCTION("""COMPUTED_VALUE"""),"User need to able to access website using browser") -> User need to able to access website using browser | F25: =IFERROR(__xludf.DUMMYFUNCTION("""COMPUTED_VALUE"""),"1. Open website of ParentBridge 2. Login using valid credentials 3. click on expense") -> 1. Open website of ParentBridge 2. Login using valid credentials 3. click on expense | G25: =IFERROR(__xludf.DUMMYFUNCTION("""COMPUTED_VALUE"""),"USER CREDENTIAL") -> USER CREDENTIAL | H25: =IFERROR(__xludf.DUMMYFUNCTION("""COMPUTED_VALUE"""),"Expenses should be displayed accurately.") -> Expenses should be displayed accurately. | I25: =IFERROR(__xludf.DUMMYFUNCTION("""COMPUTED_VALUE"""),"Mismatch has been noticed between the parent and co-parent expense data.") -> Mismatch has been noticed between the parent and co-parent expense data. | J25: =IFERROR(__xludf.DUMMYFUNCTION("""COMPUTED_VALUE"""),"Fail") -> Fail | K25: =IFERROR(__xludf.DUMMYFUNCTION("""COMPUTED_VALUE"""),"High") -> High | L25: =IFERROR(__xludf.DUMMYFUNCTION("""COMPUTED_VALUE"""),"035.png") -> 035.png | N25: =IFERROR(__xludf.DUMMYFUNCTION("""COMPUTED_VALUE"""),"Unsolved") -> Unsolved | O25: =IFERROR(__xludf.DUMMYFUNCTION("""COMPUTED_VALUE"""),"Back-End") -> Back-End | P25: =IFERROR(__xludf.DUMMYFUNCTION("""COMPUTED_VALUE"""),"Backend is not giving the data") -> Backend is not giving the data | Q25: =IFERROR(__xludf.DUMMYFUNCTION("""COMPUTED_VALUE"""),"Fahad") -> Fahad
A26: BR-016 | B26: =IFERROR(__xludf.DUMMYFUNCTION("""COMPUTED_VALUE"""),"Home") -> Home | C26: =IFERROR(__xludf.DUMMYFUNCTION("""COMPUTED_VALUE"""),"Expense") -> Expense | D26: =IFERROR(__xludf.DUMMYFUNCTION("""COMPUTED_VALUE"""),"Display issue with the total expense calculation has been noticed.") -> Display issue with the total expense calculation has been noticed. | E26: =IFERROR(__xludf.DUMMYFUNCTION("""COMPUTED_VALUE"""),"User need to able to access website using browser") -> User need to able to access website using browser | F26: =IFERROR(__xludf.DUMMYFUNCTION("""COMPUTED_VALUE"""),"1. Open website of ParentBridge 2. Login using valid credentials 3. click on expense") -> 1. Open website of ParentBridge 2. Login using valid credentials 3. click on expense | G26: =IFERROR(__xludf.DUMMYFUNCTION("""COMPUTED_VALUE"""),"USER CREDENTIAL") -> USER CREDENTIAL | H26: =IFERROR(__xludf.DUMMYFUNCTION("""COMPUTED_VALUE"""),"Calculated amount should be accurately displayed.") -> Calculated amount should be accurately displayed. | I26: =IFERROR(__xludf.DUMMYFUNCTION("""COMPUTED_VALUE"""),"Miscalculation has been spotted in the expense tab.") -> Miscalculation has been spotted in the expense tab. | J26: =IFERROR(__xludf.DUMMYFUNCTION("""COMPUTED_VALUE"""),"Fail") -> Fail | K26: =IFERROR(__xludf.DUMMYFUNCTION("""COMPUTED_VALUE"""),"High") -> High | L26: =IFERROR(__xludf.DUMMYFUNCTION("""COMPUTED_VALUE"""),"036.png") -> 036.png | N26: =IFERROR(__xludf.DUMMYFUNCTION("""COMPUTED_VALUE"""),"Unsolved") -> Unsolved | O26: =IFERROR(__xludf.DUMMYFUNCTION("""COMPUTED_VALUE"""),"Back-End") -> Back-End | P26: =IFERROR(__xludf.DUMMYFUNCTION("""COMPUTED_VALUE"""),"Backend needs to be fixed.") -> Backend needs to be fixed. | Q26: =IFERROR(__xludf.DUMMYFUNCTION("""COMPUTED_VALUE"""),"Fahad") -> Fahad
A27: BR-017 | B27: =IFERROR(__xludf.DUMMYFUNCTION("""COMPUTED_VALUE"""),"Home") -> Home | C27: =IFERROR(__xludf.DUMMYFUNCTION("""COMPUTED_VALUE"""),"Home") -> Home | D27: =IFERROR(__xludf.DUMMYFUNCTION("""COMPUTED_VALUE"""),"Quick access settings button isn’t working.") -> Quick access settings button isn’t working. | E27: =IFERROR(__xludf.DUMMYFUNCTION("""COMPUTED_VALUE"""),"User need to able to access website using browser") -> User need to able to access website using browser | F27: =IFERROR(__xludf.DUMMYFUNCTION("""COMPUTED_VALUE"""),"1. Open website of ParentBridge 2. Login using valid credential 3. goto Home 4. goto quick access section") -> 1. Open website of ParentBridge 2. Login using valid credential 3. goto Home 4. goto quick access section | G27: =IFERROR(__xludf.DUMMYFUNCTION("""COMPUTED_VALUE"""),"USER CREDENTIAL") -> USER CREDENTIAL | H27: =IFERROR(__xludf.DUMMYFUNCTION("""COMPUTED_VALUE"""),"User should be able to set quick access manually") -> User should be able to set quick access manually | I27: =IFERROR(__xludf.DUMMYFUNCTION("""COMPUTED_VALUE"""),"Quick access setup failed on the user’s side.") -> Quick access setup failed on the user’s side. | J27: =IFERROR(__xludf.DUMMYFUNCTION("""COMPUTED_VALUE"""),"Fail") -> Fail | K27: =IFERROR(__xludf.DUMMYFUNCTION("""COMPUTED_VALUE"""),"Medium") -> Medium | L27: =IFERROR(__xludf.DUMMYFUNCTION("""COMPUTED_VALUE"""),"015.png") -> 015.png | N27: =IFERROR(__xludf.DUMMYFUNCTION("""COMPUTED_VALUE"""),"Solved") -> Solved | O27: =IFERROR(__xludf.DUMMYFUNCTION("""COMPUTED_VALUE"""),"Front-End") -> Front-End | Q27: =IFERROR(__xludf.DUMMYFUNCTION("""COMPUTED_VALUE"""),"Fahad") -> Fahad
A28: BR-018 | B28: =IFERROR(__xludf.DUMMYFUNCTION("""COMPUTED_VALUE"""),"Home") -> Home | C28: =IFERROR(__xludf.DUMMYFUNCTION("""COMPUTED_VALUE"""),"Home") -> Home | D28: =IFERROR(__xludf.DUMMYFUNCTION("""COMPUTED_VALUE"""),"Failed to redirect user to calender ") -> Failed to redirect user to calender | E28: =IFERROR(__xludf.DUMMYFUNCTION("""COMPUTED_VALUE"""),"User need to able to access website using browser") -> User need to able to access website using browser | F28: =IFERROR(__xludf.DUMMYFUNCTION("""COMPUTED_VALUE"""),"1. Open website of ParentBridge 2. Login using valid credential 3. goto Home 4. goto up comming events section") -> 1. Open website of ParentBridge 2. Login using valid credential 3. goto Home 4. goto up comming events section | G28: =IFERROR(__xludf.DUMMYFUNCTION("""COMPUTED_VALUE"""),"USER CREDENTIAL") -> USER CREDENTIAL | H28: =IFERROR(__xludf.DUMMYFUNCTION("""COMPUTED_VALUE"""),"User should be redirected to the desired page when clicking the quick access links") -> User should be redirected to the desired page when clicking the quick access links | I28: =IFERROR(__xludf.DUMMYFUNCTION("""COMPUTED_VALUE"""),"Could not redirect the user to the intended location.") -> Could not redirect the user to the intended location. | J28: =IFERROR(__xludf.DUMMYFUNCTION("""COMPUTED_VALUE"""),"Fail") -> Fail | K28: =IFERROR(__xludf.DUMMYFUNCTION("""COMPUTED_VALUE"""),"High") -> High | L28: =IFERROR(__xludf.DUMMYFUNCTION("""COMPUTED_VALUE"""),"016.png") -> 016.png | N28: =IFERROR(__xludf.DUMMYFUNCTION("""COMPUTED_VALUE"""),"Solved") -> Solved | O28: =IFERROR(__xludf.DUMMYFUNCTION("""COMPUTED_VALUE"""),"Front-End") -> Front-End | Q28: =IFERROR(__xludf.DUMMYFUNCTION("""COMPUTED_VALUE"""),"Fahad") -> Fahad
A29: BR-019 | B29: =IFERROR(__xludf.DUMMYFUNCTION("""COMPUTED_VALUE"""),"Home") -> Home | C29: =IFERROR(__xludf.DUMMYFUNCTION("""COMPUTED_VALUE"""),"Home") -> Home | D29: =IFERROR(__xludf.DUMMYFUNCTION("""COMPUTED_VALUE"""),"Responsiveness didn’t work.") -> Responsiveness didn’t work. | E29: =IFERROR(__xludf.DUMMYFUNCTION("""COMPUTED_VALUE"""),"User need to able to access website using browser") -> User need to able to access website using browser | F29: =IFERROR(__xludf.DUMMYFUNCTION("""COMPUTED_VALUE"""),"1. Open website of ParentBridge 2. Login using valid credentials") -> 1. Open website of ParentBridge 2. Login using valid credentials | G29: =IFERROR(__xludf.DUMMYFUNCTION("""COMPUTED_VALUE"""),"USER CREDENTIAL") -> USER CREDENTIAL | H29: =IFERROR(__xludf.DUMMYFUNCTION("""COMPUTED_VALUE"""),"Web app should be responsive and adapt seamlessly to any device.") -> Web app should be responsive and adapt seamlessly to any device. | I29: =IFERROR(__xludf.DUMMYFUNCTION("""COMPUTED_VALUE"""),"Sidebar failed to display responsive mode.") -> Sidebar failed to display responsive mode. | J29: =IFERROR(__xludf.DUMMYFUNCTION("""COMPUTED_VALUE"""),"Fail") -> Fail | K29: =IFERROR(__xludf.DUMMYFUNCTION("""COMPUTED_VALUE"""),"High") -> High | L29: =IFERROR(__xludf.DUMMYFUNCTION("""COMPUTED_VALUE"""),"031.png") -> 031.png | N29: =IFERROR(__xludf.DUMMYFUNCTION("""COMPUTED_VALUE"""),"Solved") -> Solved | O29: =IFERROR(__xludf.DUMMYFUNCTION("""COMPUTED_VALUE"""),"Front-End") -> Front-End | Q29: =IFERROR(__xludf.DUMMYFUNCTION("""COMPUTED_VALUE"""),"Fahad") -> Fahad
A30: BR-020 | B30: =IFERROR(__xludf.DUMMYFUNCTION("""COMPUTED_VALUE"""),"Home") -> Home | C30: =IFERROR(__xludf.DUMMYFUNCTION("""COMPUTED_VALUE"""),"Settings") -> Settings | D30: =IFERROR(__xludf.DUMMYFUNCTION("""COMPUTED_VALUE"""),"Logout button should be positioned in the left section.") -> Logout button should be positioned in the left section. | E30: =IFERROR(__xludf.DUMMYFUNCTION("""COMPUTED_VALUE"""),"User need to able to access website using browser") -> User need to able to access website using browser | F30: =IFERROR(__xludf.DUMMYFUNCTION("""COMPUTED_VALUE"""),"1. Open website of ParentBridge 2. Login using valid credentials 3. click on settings") -> 1. Open website of ParentBridge 2. Login using valid credentials 3. click on settings | G30: =IFERROR(__xludf.DUMMYFUNCTION("""COMPUTED_VALUE"""),"USER CREDENTIAL") -> USER CREDENTIAL | H30: =IFERROR(__xludf.DUMMYFUNCTION("""COMPUTED_VALUE"""),"Logout button should be placed below the sidebar for convenient access.") -> Logout button should be placed below the sidebar for convenient access. | I30: =IFERROR(__xludf.DUMMYFUNCTION("""COMPUTED_VALUE"""),"Logout button is under setting tab") -> Logout button is under setting tab | J30: =IFERROR(__xludf.DUMMYFUNCTION("""COMPUTED_VALUE"""),"Fail") -> Fail | K30: =IFERROR(__xludf.DUMMYFUNCTION("""COMPUTED_VALUE"""),"Medium") -> Medium | L30: =IFERROR(__xludf.DUMMYFUNCTION("""COMPUTED_VALUE"""),"030.png") -> 030.png | N30: =IFERROR(__xludf.DUMMYFUNCTION("""COMPUTED_VALUE"""),"Solved") -> Solved | O30: =IFERROR(__xludf.DUMMYFUNCTION("""COMPUTED_VALUE"""),"Front-End") -> Front-End | Q30: =IFERROR(__xludf.DUMMYFUNCTION("""COMPUTED_VALUE"""),"Fahad") -> Fahad
A31: BR-021 | B31: =IFERROR(__xludf.DUMMYFUNCTION("""COMPUTED_VALUE"""),"Login") -> Login | C31: =IFERROR(__xludf.DUMMYFUNCTION("""COMPUTED_VALUE"""),"Forget Password") -> Forget Password | D31: =IFERROR(__xludf.DUMMYFUNCTION("""COMPUTED_VALUE"""),"The forgot password section failed to display the correct error message.") -> The forgot password section failed to display the correct error message. | E31: =IFERROR(__xludf.DUMMYFUNCTION("""COMPUTED_VALUE"""),"User need to able to access website using browser") -> User need to able to access website using browser | F31: =IFERROR(__xludf.DUMMYFUNCTION("""COMPUTED_VALUE"""),"1. Open website of ParentBridge 2. Goto Login Page 3. Click on Forget Password") -> 1. Open website of ParentBridge 2. Goto Login Page 3. Click on Forget Password | G31: =IFERROR(__xludf.DUMMYFUNCTION("""COMPUTED_VALUE"""),"N/A") -> N/A | H31: =IFERROR(__xludf.DUMMYFUNCTION("""COMPUTED_VALUE"""),"The error should clearly display the exact problem.") -> The error should clearly display the exact problem. | I31: =IFERROR(__xludf.DUMMYFUNCTION("""COMPUTED_VALUE"""),"The user was not found in the database, and the system returned a 400 error code, which doesn’t seem accurate from the user’s side.") -> The user was not found in the database, and the system returned a 400 error code, which doesn’t seem accurate from the user’s side. | J31: =IFERROR(__xludf.DUMMYFUNCTION("""COMPUTED_VALUE"""),"Fail") -> Fail | K31: =IFERROR(__xludf.DUMMYFUNCTION("""COMPUTED_VALUE"""),"High") -> High | L31: =IFERROR(__xludf.DUMMYFUNCTION("""COMPUTED_VALUE"""),"003.png") -> 003.png | N31: =IFERROR(__xludf.DUMMYFUNCTION("""COMPUTED_VALUE"""),"Solved") -> Solved | O31: =IFERROR(__xludf.DUMMYFUNCTION("""COMPUTED_VALUE"""),"Front-End") -> Front-End | Q31: =IFERROR(__xludf.DUMMYFUNCTION("""COMPUTED_VALUE"""),"Fahad") -> Fahad
A32: BR-022 | B32: =IFERROR(__xludf.DUMMYFUNCTION("""COMPUTED_VALUE"""),"Onboarding") -> Onboarding | C32: =IFERROR(__xludf.DUMMYFUNCTION("""COMPUTED_VALUE"""),"Onboarding") -> Onboarding | D32: =IFERROR(__xludf.DUMMYFUNCTION("""COMPUTED_VALUE"""),"Secure route has not been implemented yet.") -> Secure route has not been implemented yet. | E32: =IFERROR(__xludf.DUMMYFUNCTION("""COMPUTED_VALUE"""),"User need to able to access website using browser") -> User need to able to access website using browser | F32: =IFERROR(__xludf.DUMMYFUNCTION("""COMPUTED_VALUE"""),"1. Open website of ParentBridge 2. Goto Login Page 3. Goto /accout-setup route ") -> 1. Open website of ParentBridge 2. Goto Login Page 3. Goto /accout-setup route | G32: =IFERROR(__xludf.DUMMYFUNCTION("""COMPUTED_VALUE"""),"USER CREDENTIAL") -> USER CREDENTIAL | H32: =IFERROR(__xludf.DUMMYFUNCTION("""COMPUTED_VALUE"""),"Users should not be allowed to change the route manually.") -> Users should not be allowed to change the route manually. | I32: =IFERROR(__xludf.DUMMYFUNCTION("""COMPUTED_VALUE"""),"User can manually change the route, which could raise security concerns.") -> User can manually change the route, which could raise security concerns. | J32: =IFERROR(__xludf.DUMMYFUNCTION("""COMPUTED_VALUE"""),"Fail") -> Fail | K32: =IFERROR(__xludf.DUMMYFUNCTION("""COMPUTED_VALUE"""),"High") -> High | L32: =IFERROR(__xludf.DUMMYFUNCTION("""COMPUTED_VALUE"""),"006.mp4") -> 006.mp4 | N32: =IFERROR(__xludf.DUMMYFUNCTION("""COMPUTED_VALUE"""),"Solved") -> Solved | O32: =IFERROR(__xludf.DUMMYFUNCTION("""COMPUTED_VALUE"""),"Front-End") -> Front-End | Q32: =IFERROR(__xludf.DUMMYFUNCTION("""COMPUTED_VALUE"""),"Fahad") -> Fahad
A33: BR-023 | B33: =IFERROR(__xludf.DUMMYFUNCTION("""COMPUTED_VALUE"""),"Settings") -> Settings | C33: =IFERROR(__xludf.DUMMYFUNCTION("""COMPUTED_VALUE"""),"Help and Support") -> Help and Support | D33: =IFERROR(__xludf.DUMMYFUNCTION("""COMPUTED_VALUE"""),"Call support is not integrated yet.") -> Call support is not integrated yet. | E33: =IFERROR(__xludf.DUMMYFUNCTION("""COMPUTED_VALUE"""),"User need to able to access website using browser") -> User need to able to access website using browser | F33: =IFERROR(__xludf.DUMMYFUNCTION("""COMPUTED_VALUE"""),"1. Open website of ParentBridge 2. Login using valid credentials 3. click on settings 4. click on Help and Support") -> 1. Open website of ParentBridge 2. Login using valid credentials 3. click on settings 4. click on Help and Support | G33: =IFERROR(__xludf.DUMMYFUNCTION("""COMPUTED_VALUE"""),"USER CREDENTIAL") -> USER CREDENTIAL | H33: =IFERROR(__xludf.DUMMYFUNCTION("""COMPUTED_VALUE"""),"Call support button should be implemented flawlessly.") -> Call support button should be implemented flawlessly. | I33: =IFERROR(__xludf.DUMMYFUNCTION("""COMPUTED_VALUE"""),"Call support feature hasn’t been set up yet.") -> Call support feature hasn’t been set up yet. | J33: =IFERROR(__xludf.DUMMYFUNCTION("""COMPUTED_VALUE"""),"Fail") -> Fail | K33: =IFERROR(__xludf.DUMMYFUNCTION("""COMPUTED_VALUE"""),"High") -> High | L33: =IFERROR(__xludf.DUMMYFUNCTION("""COMPUTED_VALUE"""),"038.png") -> 038.png | N33: =IFERROR(__xludf.DUMMYFUNCTION("""COMPUTED_VALUE"""),"Unsolved") -> Unsolved | P33: =IFERROR(__xludf.DUMMYFUNCTION("""COMPUTED_VALUE"""),"I need the support phone number") -> I need the support phone number | Q33: =IFERROR(__xludf.DUMMYFUNCTION("""COMPUTED_VALUE"""),"Fahad") -> Fahad
A34: BR-024 | B34: =IFERROR(__xludf.DUMMYFUNCTION("""COMPUTED_VALUE"""),"Settings") -> Settings | C34: =IFERROR(__xludf.DUMMYFUNCTION("""COMPUTED_VALUE"""),"Help and Support") -> Help and Support | D34: =IFERROR(__xludf.DUMMYFUNCTION("""COMPUTED_VALUE"""),"Email support hasn’t been set up yet.") -> Email support hasn’t been set up yet. | E34: =IFERROR(__xludf.DUMMYFUNCTION("""COMPUTED_VALUE"""),"User need to able to access website using browser") -> User need to able to access website using browser | F34: =IFERROR(__xludf.DUMMYFUNCTION("""COMPUTED_VALUE"""),"1. Open website of ParentBridge 2. Login using valid credentials 3. click on settings 4. click on Help and Support") -> 1. Open website of ParentBridge 2. Login using valid credentials 3. click on settings 4. click on Help and Support | G34: =IFERROR(__xludf.DUMMYFUNCTION("""COMPUTED_VALUE"""),"USER CREDENTIAL") -> USER CREDENTIAL | H34: =IFERROR(__xludf.DUMMYFUNCTION("""COMPUTED_VALUE"""),"Email support should be implemented precisely.") -> Email support should be implemented precisely. | I34: =IFERROR(__xludf.DUMMYFUNCTION("""COMPUTED_VALUE"""),"Feature hasn't been implemented yet.") -> Feature hasn't been implemented yet. | J34: =IFERROR(__xludf.DUMMYFUNCTION("""COMPUTED_VALUE"""),"Fail") -> Fail | K34: =IFERROR(__xludf.DUMMYFUNCTION("""COMPUTED_VALUE"""),"High") -> High | L34: =IFERROR(__xludf.DUMMYFUNCTION("""COMPUTED_VALUE"""),"039.png") -> 039.png | N34: =IFERROR(__xludf.DUMMYFUNCTION("""COMPUTED_VALUE"""),"Unsolved") -> Unsolved | P34: =IFERROR(__xludf.DUMMYFUNCTION("""COMPUTED_VALUE"""),"I need teh support email address") -> I need teh support email address | Q34: =IFERROR(__xludf.DUMMYFUNCTION("""COMPUTED_VALUE"""),"Fahad") -> Fahad
A35: BR-025 | B35: =IFERROR(__xludf.DUMMYFUNCTION("""COMPUTED_VALUE"""),"Settings") -> Settings | C35: =IFERROR(__xludf.DUMMYFUNCTION("""COMPUTED_VALUE"""),"Help and Support") -> Help and Support | D35: =IFERROR(__xludf.DUMMYFUNCTION("""COMPUTED_VALUE"""),"Live chat support hasn’t been set up yet.") -> Live chat support hasn’t been set up yet. | E35: =IFERROR(__xludf.DUMMYFUNCTION("""COMPUTED_VALUE"""),"User need to able to access website using browser") -> User need to able to access website using browser | F35: =IFERROR(__xludf.DUMMYFUNCTION("""COMPUTED_VALUE"""),"1. Open website of ParentBridge 2. Login using valid credentials 3. click on settings 4. click on Help and Support") -> 1. Open website of ParentBridge 2. Login using valid credentials 3. click on settings 4. click on Help and Support | G35: =IFERROR(__xludf.DUMMYFUNCTION("""COMPUTED_VALUE"""),"USER CREDENTIAL") -> USER CREDENTIAL | H35: =IFERROR(__xludf.DUMMYFUNCTION("""COMPUTED_VALUE"""),"Live chat support should be implemented precisely.") -> Live chat support should be implemented precisely. | I35: =IFERROR(__xludf.DUMMYFUNCTION("""COMPUTED_VALUE"""),"Feature hasn't been implemented yet.") -> Feature hasn't been implemented yet. | J35: =IFERROR(__xludf.DUMMYFUNCTION("""COMPUTED_VALUE"""),"Fail") -> Fail | K35: =IFERROR(__xludf.DUMMYFUNCTION("""COMPUTED_VALUE"""),"High") -> High | L35: =IFERROR(__xludf.DUMMYFUNCTION("""COMPUTED_VALUE"""),"040.png") -> 040.png | N35: =IFERROR(__xludf.DUMMYFUNCTION("""COMPUTED_VALUE"""),"Solved") -> Solved | P35: =IFERROR(__xludf.DUMMYFUNCTION("""COMPUTED_VALUE"""),"Its not in figma so I removed it") -> Its not in figma so I removed it | Q35: =IFERROR(__xludf.DUMMYFUNCTION("""COMPUTED_VALUE"""),"Fahad") -> Fahad
A36: BR-026 | B36: =IFERROR(__xludf.DUMMYFUNCTION("""COMPUTED_VALUE"""),"Settings") -> Settings | C36: =IFERROR(__xludf.DUMMYFUNCTION("""COMPUTED_VALUE"""),"Profile Information") -> Profile Information | D36: =IFERROR(__xludf.DUMMYFUNCTION("""COMPUTED_VALUE"""),"Email field missing in profile information tab") -> Email field missing in profile information tab | E36: =IFERROR(__xludf.DUMMYFUNCTION("""COMPUTED_VALUE"""),"User need to able to access website using browser") -> User need to able to access website using browser | F36: =IFERROR(__xludf.DUMMYFUNCTION("""COMPUTED_VALUE"""),"1. Open website of ParentBridge 2. Login using valid credentials 3. click on settings 4. click on profile information") -> 1. Open website of ParentBridge 2. Login using valid credentials 3. click on settings 4. click on profile information | G36: =IFERROR(__xludf.DUMMYFUNCTION("""COMPUTED_VALUE"""),"USER CREDENTIAL") -> USER CREDENTIAL | H36: =IFERROR(__xludf.DUMMYFUNCTION("""COMPUTED_VALUE"""),"Email field should be visible in the profile information.") -> Email field should be visible in the profile information. | I36: =IFERROR(__xludf.DUMMYFUNCTION("""COMPUTED_VALUE"""),"Email name field is missing in the profile information section.") -> Email name field is missing in the profile information section. | J36: =IFERROR(__xludf.DUMMYFUNCTION("""COMPUTED_VALUE"""),"Fail") -> Fail | K36: =IFERROR(__xludf.DUMMYFUNCTION("""COMPUTED_VALUE"""),"Medium") -> Medium | L36: =IFERROR(__xludf.DUMMYFUNCTION("""COMPUTED_VALUE"""),"029.png") -> 029.png | N36: =IFERROR(__xludf.DUMMYFUNCTION("""COMPUTED_VALUE"""),"Unsolved") -> Unsolved | O36: =IFERROR(__xludf.DUMMYFUNCTION("""COMPUTED_VALUE"""),"Back-End") -> Back-End | P36: =IFERROR(__xludf.DUMMYFUNCTION("""COMPUTED_VALUE"""),"Email is not coming in profile api") -> Email is not coming in profile api | Q36: =IFERROR(__xludf.DUMMYFUNCTION("""COMPUTED_VALUE"""),"Fahad") -> Fahad
A37: BR-027 | B37: =IFERROR(__xludf.DUMMYFUNCTION("""COMPUTED_VALUE"""),"Settings") -> Settings | C37: =IFERROR(__xludf.DUMMYFUNCTION("""COMPUTED_VALUE"""),"Profile Information") -> Profile Information | D37: =IFERROR(__xludf.DUMMYFUNCTION("""COMPUTED_VALUE"""),"Co-parent's contact number is not showing up in the user’s co-parent information section.") -> Co-parent's contact number is not showing up in the user’s co-parent information section. | E37: =IFERROR(__xludf.DUMMYFUNCTION("""COMPUTED_VALUE"""),"User need to able to access website using browser") -> User need to able to access website using browser | F37: =IFERROR(__xludf.DUMMYFUNCTION("""COMPUTED_VALUE"""),"1. Open website of ParentBridge 2. Login using valid credentials 3. click on settings 4. click on co-parent information") -> 1. Open website of ParentBridge 2. Login using valid credentials 3. click on settings 4. click on co-parent information | G37: =IFERROR(__xludf.DUMMYFUNCTION("""COMPUTED_VALUE"""),"USER CREDENTIAL") -> USER CREDENTIAL | H37: =IFERROR(__xludf.DUMMYFUNCTION("""COMPUTED_VALUE"""),"Contact should be displayed in both parents' profiles") -> Contact should be displayed in both parents' profiles | I37: =IFERROR(__xludf.DUMMYFUNCTION("""COMPUTED_VALUE"""),"Co-parent’s profile is missing a contact number.") -> Co-parent’s profile is missing a contact number. | J37: =IFERROR(__xludf.DUMMYFUNCTION("""COMPUTED_VALUE"""),"Fail") -> Fail | K37: =IFERROR(__xludf.DUMMYFUNCTION("""COMPUTED_VALUE"""),"High") -> High | L37: =IFERROR(__xludf.DUMMYFUNCTION("""COMPUTED_VALUE"""),"032.png") -> 032.png | N37: =IFERROR(__xludf.DUMMYFUNCTION("""COMPUTED_VALUE"""),"Unsolved") -> Unsolved | O37: =IFERROR(__xludf.DUMMYFUNCTION("""COMPUTED_VALUE"""),"Back-End") -> Back-End | P37: =IFERROR(__xludf.DUMMYFUNCTION("""COMPUTED_VALUE"""),"Backend, please check this issue because I am showing all the fields properly") -> Backend, please check this issue because I am showing all the fields properly | Q37: =IFERROR(__xludf.DUMMYFUNCTION("""COMPUTED_VALUE"""),"Fahad") -> Fahad
A38: BR-028 | B38: =IFERROR(__xludf.DUMMYFUNCTION("""COMPUTED_VALUE"""),"Settings") -> Settings | C38: =IFERROR(__xludf.DUMMYFUNCTION("""COMPUTED_VALUE"""),"Profile Information") -> Profile Information | D38: =IFERROR(__xludf.DUMMYFUNCTION("""COMPUTED_VALUE"""),"Name, state, and phone are typically required to create an account, but you can still set one up without them.") -> Name, state, and phone are typically required to create an account, but you can still set one up without them. | E38: =IFERROR(__xludf.DUMMYFUNCTION("""COMPUTED_VALUE"""),"User need to able to access website using browser") -> User need to able to access website using browser | F38: =IFERROR(__xludf.DUMMYFUNCTION("""COMPUTED_VALUE"""),"1. Open website of ParentBridge 2. Login using valid credentials 3. click on settings 4. click on co-parent information") -> 1. Open website of ParentBridge 2. Login using valid credentials 3. click on settings 4. click on co-parent information | G38: =IFERROR(__xludf.DUMMYFUNCTION("""COMPUTED_VALUE"""),"USER CREDENTIAL") -> USER CREDENTIAL | H38: =IFERROR(__xludf.DUMMYFUNCTION("""COMPUTED_VALUE"""),"Profile setup page should include the required field.") -> Profile setup page should include the required field. | I38: =IFERROR(__xludf.DUMMYFUNCTION("""COMPUTED_VALUE"""),"Required fields are not being captured during profile setup.") -> Required fields are not being captured during profile setup. | J38: =IFERROR(__xludf.DUMMYFUNCTION("""COMPUTED_VALUE"""),"Fail") -> Fail | K38: =IFERROR(__xludf.DUMMYFUNCTION("""COMPUTED_VALUE"""),"High") -> High | L38: =IFERROR(__xludf.DUMMYFUNCTION("""COMPUTED_VALUE"""),"037.png") -> 037.png | N38: =IFERROR(__xludf.DUMMYFUNCTION("""COMPUTED_VALUE"""),"Unsolved") -> Unsolved | P38: =IFERROR(__xludf.DUMMYFUNCTION("""COMPUTED_VALUE"""),"User cant create account without account setup") -> User cant create account without account setup | Q38: =IFERROR(__xludf.DUMMYFUNCTION("""COMPUTED_VALUE"""),"Fahad") -> Fahad
A39: BR-029 | B39: =IFERROR(__xludf.DUMMYFUNCTION("""COMPUTED_VALUE"""),"Signup") -> Signup | C39: =IFERROR(__xludf.DUMMYFUNCTION("""COMPUTED_VALUE"""),"OTP") -> OTP | D39: =IFERROR(__xludf.DUMMYFUNCTION("""COMPUTED_VALUE"""),"Able to signup with expired OTP") -> Able to signup with expired OTP | E39: =IFERROR(__xludf.DUMMYFUNCTION("""COMPUTED_VALUE"""),"User need to able to access website using browser") -> User need to able to access website using browser | F39: =IFERROR(__xludf.DUMMYFUNCTION("""COMPUTED_VALUE"""),"1. Open website of ParentBridge 2. Goto Login Page 3. Click on SignUp 4. Enter expired OTP and click on verify") -> 1. Open website of ParentBridge 2. Goto Login Page 3. Click on SignUp 4. Enter expired OTP and click on verify | G39: =IFERROR(__xludf.DUMMYFUNCTION("""COMPUTED_VALUE"""),"USER CREDENTIAL") -> USER CREDENTIAL | H39: =IFERROR(__xludf.DUMMYFUNCTION("""COMPUTED_VALUE"""),"User shouldn’t be able to verify their login credentials using an expired OTP.") -> User shouldn’t be able to verify their login credentials using an expired OTP. | I39: =IFERROR(__xludf.DUMMYFUNCTION("""COMPUTED_VALUE"""),"Users can verify their profile using an expired OTP.") -> Users can verify their profile using an expired OTP. | J39: =IFERROR(__xludf.DUMMYFUNCTION("""COMPUTED_VALUE"""),"Fail") -> Fail | K39: =IFERROR(__xludf.DUMMYFUNCTION("""COMPUTED_VALUE"""),"High") -> High | L39: =IFERROR(__xludf.DUMMYFUNCTION("""COMPUTED_VALUE"""),"005.mp4") -> 005.mp4 | N39: =IFERROR(__xludf.DUMMYFUNCTION("""COMPUTED_VALUE"""),"Solved") -> Solved | O39: =IFERROR(__xludf.DUMMYFUNCTION("""COMPUTED_VALUE"""),"Front-End") -> Front-End | Q39: =IFERROR(__xludf.DUMMYFUNCTION("""COMPUTED_VALUE"""),"Fahad") -> Fahad
A40: BR-030 | B40: =IFERROR(__xludf.DUMMYFUNCTION("""COMPUTED_VALUE"""),"Signup") -> Signup | C40: =IFERROR(__xludf.DUMMYFUNCTION("""COMPUTED_VALUE"""),"Signup") -> Signup | D40: =IFERROR(__xludf.DUMMYFUNCTION("""COMPUTED_VALUE"""),"Failed to signup using google signin") -> Failed to signup using google signin | E40: =IFERROR(__xludf.DUMMYFUNCTION("""COMPUTED_VALUE"""),"User need to able to access website using browser") -> User need to able to access website using browser | F40: =IFERROR(__xludf.DUMMYFUNCTION("""COMPUTED_VALUE"""),"1. Open website of ParentBridge 2. Goto Login Page 3. Click on SignUp") -> 1. Open website of ParentBridge 2. Goto Login Page 3. Click on SignUp | G40: =IFERROR(__xludf.DUMMYFUNCTION("""COMPUTED_VALUE"""),"N/A") -> N/A | H40: =IFERROR(__xludf.DUMMYFUNCTION("""COMPUTED_VALUE"""),"User should be able to signup through google signup") -> User should be able to signup through google signup | I40: =IFERROR(__xludf.DUMMYFUNCTION("""COMPUTED_VALUE"""),"Unable to sign up using Google.") -> Unable to sign up using Google. | J40: =IFERROR(__xludf.DUMMYFUNCTION("""COMPUTED_VALUE"""),"Fail") -> Fail | K40: =IFERROR(__xludf.DUMMYFUNCTION("""COMPUTED_VALUE"""),"High") -> High | L40: =IFERROR(__xludf.DUMMYFUNCTION("""COMPUTED_VALUE"""),"004.png") -> 004.png | N40: =IFERROR(__xludf.DUMMYFUNCTION("""COMPUTED_VALUE"""),"Solved") -> Solved | O40: =IFERROR(__xludf.DUMMYFUNCTION("""COMPUTED_VALUE"""),"Front-End") -> Front-End | Q40: =IFERROR(__xludf.DUMMYFUNCTION("""COMPUTED_VALUE"""),"Fahad") -> Fahad
A41: BR-031 | B41: =IFERROR(__xludf.DUMMYFUNCTION("""COMPUTED_VALUE"""),"Signup") -> Signup | C41: =IFERROR(__xludf.DUMMYFUNCTION("""COMPUTED_VALUE"""),"Signup") -> Signup | D41: =IFERROR(__xludf.DUMMYFUNCTION("""COMPUTED_VALUE"""),"Dull color theme of the signup button makes users think it’s not clickable.") -> Dull color theme of the signup button makes users think it’s not clickable. | E41: =IFERROR(__xludf.DUMMYFUNCTION("""COMPUTED_VALUE"""),"User need to able to access website using browser") -> User need to able to access website using browser | F41: =IFERROR(__xludf.DUMMYFUNCTION("""COMPUTED_VALUE"""),"1. Open website of ParentBridge 2. Goto Login Page 3. Click on SignUp") -> 1. Open website of ParentBridge 2. Goto Login Page 3. Click on SignUp | G41: =IFERROR(__xludf.DUMMYFUNCTION("""COMPUTED_VALUE"""),"N/A") -> N/A | H41: =IFERROR(__xludf.DUMMYFUNCTION("""COMPUTED_VALUE"""),"Button color should be bright from the user's perspective.") -> Button color should be bright from the user's perspective. | I41: =IFERROR(__xludf.DUMMYFUNCTION("""COMPUTED_VALUE"""),"Signup button uses a dull color.") -> Signup button uses a dull color. | J41: =IFERROR(__xludf.DUMMYFUNCTION("""COMPUTED_VALUE"""),"Fail") -> Fail | K41: =IFERROR(__xludf.DUMMYFUNCTION("""COMPUTED_VALUE"""),"Low") -> Low | L41: =IFERROR(__xludf.DUMMYFUNCTION("""COMPUTED_VALUE"""),"025.png") -> 025.png | N41: =IFERROR(__xludf.DUMMYFUNCTION("""COMPUTED_VALUE"""),"Solved") -> Solved | O41: =IFERROR(__xludf.DUMMYFUNCTION("""COMPUTED_VALUE"""),"Back-End") -> Back-End | P41: =IFERROR(__xludf.DUMMYFUNCTION("""COMPUTED_VALUE"""),"It is handled by backend") -> It is handled by backend | Q41: =IFERROR(__xludf.DUMMYFUNCTION("""COMPUTED_VALUE"""),"Fahad") -> Fahad
A42: BR-032 | B42: =IFERROR(__xludf.DUMMYFUNCTION("""COMPUTED_VALUE"""),"Splash Screen") -> Splash Screen | C42: =IFERROR(__xludf.DUMMYFUNCTION("""COMPUTED_VALUE"""),"Splash Screen") -> Splash Screen | D42: =IFERROR(__xludf.DUMMYFUNCTION("""COMPUTED_VALUE"""),"""Next Button"" is not implemented") -> "Next Button" is not implemented | E42: =IFERROR(__xludf.DUMMYFUNCTION("""COMPUTED_VALUE"""),"User need to able to access website using browser") -> User need to able to access website using browser | F42: =IFERROR(__xludf.DUMMYFUNCTION("""COMPUTED_VALUE"""),"1. Open website of ParentBridge") -> 1. Open website of ParentBridge | G42: =IFERROR(__xludf.DUMMYFUNCTION("""COMPUTED_VALUE"""),"N/A") -> N/A | H42: =IFERROR(__xludf.DUMMYFUNCTION("""COMPUTED_VALUE"""),"User should be able to change pages by sliding right to left or click button") -> User should be able to change pages by sliding right to left or click button | I42: =IFERROR(__xludf.DUMMYFUNCTION("""COMPUTED_VALUE"""),"Unable to change page screen") -> Unable to change page screen | J42: =IFERROR(__xludf.DUMMYFUNCTION("""COMPUTED_VALUE"""),"Fail") -> Fail | K42: =IFERROR(__xludf.DUMMYFUNCTION("""COMPUTED_VALUE"""),"Medium") -> Medium | L42: =IFERROR(__xludf.DUMMYFUNCTION("""COMPUTED_VALUE"""),"001.png") -> 001.png | N42: =IFERROR(__xludf.DUMMYFUNCTION("""COMPUTED_VALUE"""),"Solved") -> Solved | O42: =IFERROR(__xludf.DUMMYFUNCTION("""COMPUTED_VALUE"""),"Front-End") -> Front-End | P42: =IFERROR(__xludf.DUMMYFUNCTION("""COMPUTED_VALUE"""),"Splash screen is removed") -> Splash screen is removed | Q42: =IFERROR(__xludf.DUMMYFUNCTION("""COMPUTED_VALUE"""),"Fahad") -> Fahad
A43: BR-033 | B43: =IFERROR(__xludf.DUMMYFUNCTION("""COMPUTED_VALUE"""),"Splash Screen") -> Splash Screen | C43: =IFERROR(__xludf.DUMMYFUNCTION("""COMPUTED_VALUE"""),"Splash Screen") -> Splash Screen | D43: =IFERROR(__xludf.DUMMYFUNCTION("""COMPUTED_VALUE"""),"A blank space has been spotted on the splash screen.") -> A blank space has been spotted on the splash screen. | E43: =IFERROR(__xludf.DUMMYFUNCTION("""COMPUTED_VALUE"""),"User need to able to access website using browser") -> User need to able to access website using browser | F43: =IFERROR(__xludf.DUMMYFUNCTION("""COMPUTED_VALUE"""),"1. Open website of ParentBridge") -> 1. Open website of ParentBridge | G43: =IFERROR(__xludf.DUMMYFUNCTION("""COMPUTED_VALUE"""),"N/A") -> N/A | H43: =IFERROR(__xludf.DUMMYFUNCTION("""COMPUTED_VALUE"""),"The screen should be filled with the necessary information.") -> The screen should be filled with the necessary information. | I43: =IFERROR(__xludf.DUMMYFUNCTION("""COMPUTED_VALUE"""),"A blank space has been noticed on the splash screen.") -> A blank space has been noticed on the splash screen. | J43: =IFERROR(__xludf.DUMMYFUNCTION("""COMPUTED_VALUE"""),"Fail") -> Fail | K43: =IFERROR(__xludf.DUMMYFUNCTION("""COMPUTED_VALUE"""),"Medium") -> Medium | L43: =IFERROR(__xludf.DUMMYFUNCTION("""COMPUTED_VALUE"""),"002.png") -> 002.png | N43: =IFERROR(__xludf.DUMMYFUNCTION("""COMPUTED_VALUE"""),"Solved") -> Solved | O43: =IFERROR(__xludf.DUMMYFUNCTION("""COMPUTED_VALUE"""),"Front-End") -> Front-End | P43: =IFERROR(__xludf.DUMMYFUNCTION("""COMPUTED_VALUE"""),"Splash screen is removed") -> Splash screen is removed | Q43: =IFERROR(__xludf.DUMMYFUNCTION("""COMPUTED_VALUE"""),"Fahad") -> Fahad
A44: BR-034 | B44: =IFERROR(__xludf.DUMMYFUNCTION("""COMPUTED_VALUE"""),"Subscription") -> Subscription | C44: =IFERROR(__xludf.DUMMYFUNCTION("""COMPUTED_VALUE"""),"Subscription") -> Subscription | D44: =IFERROR(__xludf.DUMMYFUNCTION("""COMPUTED_VALUE"""),"Calculation error has been noticed in ParentBridge Pro plan") -> Calculation error has been noticed in ParentBridge Pro plan | E44: =IFERROR(__xludf.DUMMYFUNCTION("""COMPUTED_VALUE"""),"User need to able to access website using browser") -> User need to able to access website using browser | F44: =IFERROR(__xludf.DUMMYFUNCTION("""COMPUTED_VALUE"""),"1. Open website of ParentBridge 2. Goto Login Page 3. Login using valid credentials 4. Fill up Basic information") -> 1. Open website of ParentBridge 2. Goto Login Page 3. Login using valid credentials 4. Fill up Basic information | G44: =IFERROR(__xludf.DUMMYFUNCTION("""COMPUTED_VALUE"""),"USER CREDENTIAL") -> USER CREDENTIAL | H44: =IFERROR(__xludf.DUMMYFUNCTION("""COMPUTED_VALUE"""),"The price plan calculation needs to be accurate on the frontend.") -> The price plan calculation needs to be accurate on the frontend. | I44: =IFERROR(__xludf.DUMMYFUNCTION("""COMPUTED_VALUE"""),"Miscalculation in the monthly and yearly plan has been noticed.") -> Miscalculation in the monthly and yearly plan has been noticed. | J44: =IFERROR(__xludf.DUMMYFUNCTION("""COMPUTED_VALUE"""),"Fail") -> Fail | K44: =IFERROR(__xludf.DUMMYFUNCTION("""COMPUTED_VALUE"""),"High") -> High | L44: =IFERROR(__xludf.DUMMYFUNCTION("""COMPUTED_VALUE"""),"010.png") -> 010.png | M44: =IFERROR(__xludf.DUMMYFUNCTION("""COMPUTED_VALUE"""),"Add discount rate ") -> Add discount rate | N44: =IFERROR(__xludf.DUMMYFUNCTION("""COMPUTED_VALUE"""),"Unsolved") -> Unsolved | O44: =IFERROR(__xludf.DUMMYFUNCTION("""COMPUTED_VALUE"""),"Front-End") -> Front-End | P44: =IFERROR(__xludf.DUMMYFUNCTION("""COMPUTED_VALUE"""),"The whole pricing is controlled from the backend only.") -> The whole pricing is controlled from the backend only. | Q44: =IFERROR(__xludf.DUMMYFUNCTION("""COMPUTED_VALUE"""),"Fahad") -> Fahad
A45: BR-035 | B45: =IFERROR(__xludf.DUMMYFUNCTION("""COMPUTED_VALUE"""),"Subscription") -> Subscription | C45: =IFERROR(__xludf.DUMMYFUNCTION("""COMPUTED_VALUE"""),"Subscription") -> Subscription | D45: =IFERROR(__xludf.DUMMYFUNCTION("""COMPUTED_VALUE"""),"Calculation error has been noticed in ParentBridge Pro Plus plan") -> Calculation error has been noticed in ParentBridge Pro Plus plan | E45: =IFERROR(__xludf.DUMMYFUNCTION("""COMPUTED_VALUE"""),"User need to able to access website using browser") -> User need to able to access website using browser | F45: =IFERROR(__xludf.DUMMYFUNCTION("""COMPUTED_VALUE"""),"1. Open website of ParentBridge 2. Goto Login Page 3. Login using valid credentials 4. Fill up Basic information") -> 1. Open website of ParentBridge 2. Goto Login Page 3. Login using valid credentials 4. Fill up Basic information | G45: =IFERROR(__xludf.DUMMYFUNCTION("""COMPUTED_VALUE"""),"USER CREDENTIAL") -> USER CREDENTIAL | H45: =IFERROR(__xludf.DUMMYFUNCTION("""COMPUTED_VALUE"""),"The price plan calculation needs to be accurate on the frontend.") -> The price plan calculation needs to be accurate on the frontend. | I45: =IFERROR(__xludf.DUMMYFUNCTION("""COMPUTED_VALUE"""),"Miscalculation in the monthly and yearly plan has been noticed.") -> Miscalculation in the monthly and yearly plan has been noticed. | J45: =IFERROR(__xludf.DUMMYFUNCTION("""COMPUTED_VALUE"""),"Fail") -> Fail | K45: =IFERROR(__xludf.DUMMYFUNCTION("""COMPUTED_VALUE"""),"High") -> High | L45: =IFERROR(__xludf.DUMMYFUNCTION("""COMPUTED_VALUE"""),"011.png") -> 011.png | M45: =IFERROR(__xludf.DUMMYFUNCTION("""COMPUTED_VALUE"""),"Add discount rate ") -> Add discount rate | N45: =IFERROR(__xludf.DUMMYFUNCTION("""COMPUTED_VALUE"""),"Unsolved") -> Unsolved | O45: =IFERROR(__xludf.DUMMYFUNCTION("""COMPUTED_VALUE"""),"Front-End") -> Front-End | P45: =IFERROR(__xludf.DUMMYFUNCTION("""COMPUTED_VALUE"""),"The whole pricing is controlled from the backend only.") -> The whole pricing is controlled from the backend only. | Q45: =IFERROR(__xludf.DUMMYFUNCTION("""COMPUTED_VALUE"""),"Fahad") -> Fahad
A46: BR-036 | B46: =IFERROR(__xludf.DUMMYFUNCTION("""COMPUTED_VALUE"""),"Subscription") -> Subscription | C46: =IFERROR(__xludf.DUMMYFUNCTION("""COMPUTED_VALUE"""),"Subscription") -> Subscription | D46: =IFERROR(__xludf.DUMMYFUNCTION("""COMPUTED_VALUE"""),"Can't buy the plan") -> Can't buy the plan | E46: =IFERROR(__xludf.DUMMYFUNCTION("""COMPUTED_VALUE"""),"User need to able to access website using browser") -> User need to able to access website using browser | F46: =IFERROR(__xludf.DUMMYFUNCTION("""COMPUTED_VALUE"""),"1. Open website of ParentBridge 2. Goto Login Page 3. Login using valid credentials 4. Fill up Basic information 5. Click next and goto subscription page") -> 1. Open website of ParentBridge 2. Goto Login Page 3. Login using valid credentials 4. Fill up Basic information 5. Click next and goto subscription page | G46: =IFERROR(__xludf.DUMMYFUNCTION("""COMPUTED_VALUE"""),"USER CREDENTIAL") -> USER CREDENTIAL | H46: =IFERROR(__xludf.DUMMYFUNCTION("""COMPUTED_VALUE"""),"Users should not encounter errors when purchasing a plan.") -> Users should not encounter errors when purchasing a plan. | I46: =IFERROR(__xludf.DUMMYFUNCTION("""COMPUTED_VALUE"""),"Unable to complete plan purchase") -> Unable to complete plan purchase | J46: =IFERROR(__xludf.DUMMYFUNCTION("""COMPUTED_VALUE"""),"Fail") -> Fail | K46: =IFERROR(__xludf.DUMMYFUNCTION("""COMPUTED_VALUE"""),"High") -> High | L46: =IFERROR(__xludf.DUMMYFUNCTION("""COMPUTED_VALUE"""),"012.png") -> 012.png | M46: =IFERROR(__xludf.DUMMYFUNCTION("""COMPUTED_VALUE"""),"Add discount rate ") -> Add discount rate | N46: =IFERROR(__xludf.DUMMYFUNCTION("""COMPUTED_VALUE"""),"Solved") -> Solved | O46: =IFERROR(__xludf.DUMMYFUNCTION("""COMPUTED_VALUE"""),"Front-End") -> Front-End | Q46: =IFERROR(__xludf.DUMMYFUNCTION("""COMPUTED_VALUE"""),"Fahad") -> Fahad
A47: BR-037 | B47: =IFERROR(__xludf.DUMMYFUNCTION("""COMPUTED_VALUE"""),"Subscription") -> Subscription | C47: =IFERROR(__xludf.DUMMYFUNCTION("""COMPUTED_VALUE"""),"Subscription") -> Subscription | D47: =IFERROR(__xludf.DUMMYFUNCTION("""COMPUTED_VALUE"""),"Checkout page redirect to localhost url") -> Checkout page redirect to localhost url | E47: =IFERROR(__xludf.DUMMYFUNCTION("""COMPUTED_VALUE"""),"User need to able to access website using browser") -> User need to able to access website using browser | F47: =IFERROR(__xludf.DUMMYFUNCTION("""COMPUTED_VALUE"""),"1. Open website of ParentBridge 2. Goto Login Page 3. Login using valid credentials 4. Fill up Basic information 5. Click next and goto subscription page") -> 1. Open website of ParentBridge 2. Goto Login Page 3. Login using valid credentials 4. Fill up Basic information 5. Click next and goto subscription page | G47: =IFERROR(__xludf.DUMMYFUNCTION("""COMPUTED_VALUE"""),"USER CREDENTIAL") -> USER CREDENTIAL | H47: =IFERROR(__xludf.DUMMYFUNCTION("""COMPUTED_VALUE"""),"After purchasing a plan, the user should be redirected to either the home page or the payment success page.") -> After purchasing a plan, the user should be redirected to either the home page or the payment success page. | I47: =IFERROR(__xludf.DUMMYFUNCTION("""COMPUTED_VALUE"""),"After purchasing a plan, the user wasn’t redirected to the home page or the payment success page.") -> After purchasing a plan, the user wasn’t redirected to the home page or the payment success page. | J47: =IFERROR(__xludf.DUMMYFUNCTION("""COMPUTED_VALUE"""),"Fail") -> Fail | K47: =IFERROR(__xludf.DUMMYFUNCTION("""COMPUTED_VALUE"""),"High") -> High | L47: =IFERROR(__xludf.DUMMYFUNCTION("""COMPUTED_VALUE"""),"013.png") -> 013.png | N47: =IFERROR(__xludf.DUMMYFUNCTION("""COMPUTED_VALUE"""),"Solved") -> Solved | Q47: =IFERROR(__xludf.DUMMYFUNCTION("""COMPUTED_VALUE"""),"Fahad") -> Fahad
A48: BR-038 | B48: =IFERROR(__xludf.DUMMYFUNCTION("""COMPUTED_VALUE"""),"Subscription") -> Subscription | C48: =IFERROR(__xludf.DUMMYFUNCTION("""COMPUTED_VALUE"""),"Subscription") -> Subscription | D48: =IFERROR(__xludf.DUMMYFUNCTION("""COMPUTED_VALUE"""),"Yearly subscription failed on both plans.") -> Yearly subscription failed on both plans. | E48: =IFERROR(__xludf.DUMMYFUNCTION("""COMPUTED_VALUE"""),"User need to able to access website using browser") -> User need to able to access website using browser | F48: =IFERROR(__xludf.DUMMYFUNCTION("""COMPUTED_VALUE"""),"1. Open website of ParentBridge 2. Goto Login Page 3. Login using valid credentials 4. Fill up Basic information 5. Click next and goto subscription page") -> 1. Open website of ParentBridge 2. Goto Login Page 3. Login using valid credentials 4. Fill up Basic information 5. Click next and goto subscription page | G48: =IFERROR(__xludf.DUMMYFUNCTION("""COMPUTED_VALUE"""),"USER CREDENTIAL") -> USER CREDENTIAL | H48: =IFERROR(__xludf.DUMMYFUNCTION("""COMPUTED_VALUE"""),"Users should be to purchase a monthly or yearly plan on both subscriptions without any issues.") -> Users should be to purchase a monthly or yearly plan on both subscriptions without any issues. | I48: =IFERROR(__xludf.DUMMYFUNCTION("""COMPUTED_VALUE"""),"Unable to complete the purchase of the yearly subscription for either.") -> Unable to complete the purchase of the yearly subscription for either. | J48: =IFERROR(__xludf.DUMMYFUNCTION("""COMPUTED_VALUE"""),"Fail") -> Fail | K48: =IFERROR(__xludf.DUMMYFUNCTION("""COMPUTED_VALUE"""),"High") -> High | L48: =IFERROR(__xludf.DUMMYFUNCTION("""COMPUTED_VALUE"""),"026.png") -> 026.png | N48: =IFERROR(__xludf.DUMMYFUNCTION("""COMPUTED_VALUE"""),"Solved") -> Solved | O48: =IFERROR(__xludf.DUMMYFUNCTION("""COMPUTED_VALUE"""),"Back-End") -> Back-End | P48: =IFERROR(__xludf.DUMMYFUNCTION("""COMPUTED_VALUE"""),"It is handled by backend") -> It is handled by backend | Q48: =IFERROR(__xludf.DUMMYFUNCTION("""COMPUTED_VALUE"""),"Fahad") -> Fahad
A49: BR-039 | B49: =IFERROR(__xludf.DUMMYFUNCTION("""COMPUTED_VALUE"""),"Subscription") -> Subscription | C49: =IFERROR(__xludf.DUMMYFUNCTION("""COMPUTED_VALUE"""),"Subscription") -> Subscription | D49: =IFERROR(__xludf.DUMMYFUNCTION("""COMPUTED_VALUE"""),"After purchasing a plan, it should redirect to the home or dashboard page.") -> After purchasing a plan, it should redirect to the home or dashboard page. | E49: =IFERROR(__xludf.DUMMYFUNCTION("""COMPUTED_VALUE"""),"User need to able to access website using browser") -> User need to able to access website using browser | F49: =IFERROR(__xludf.DUMMYFUNCTION("""COMPUTED_VALUE"""),"1. Open website of ParentBridge 2. Goto Login Page 3. Login using valid credentials 4. Fill up Basic information 5. Click next and goto subscription page") -> 1. Open website of ParentBridge 2. Goto Login Page 3. Login using valid credentials 4. Fill up Basic information 5. Click next and goto subscription page | G49: =IFERROR(__xludf.DUMMYFUNCTION("""COMPUTED_VALUE"""),"USER CREDENTIAL") -> USER CREDENTIAL | H49: =IFERROR(__xludf.DUMMYFUNCTION("""COMPUTED_VALUE"""),"After a successful purchase, the user should be redirected to the home or dashboard page.") -> After a successful purchase, the user should be redirected to the home or dashboard page. | I49: =IFERROR(__xludf.DUMMYFUNCTION("""COMPUTED_VALUE"""),"Redirecting to the subscription page doesn’t make sense.") -> Redirecting to the subscription page doesn’t make sense. | J49: =IFERROR(__xludf.DUMMYFUNCTION("""COMPUTED_VALUE"""),"Fail") -> Fail | K49: =IFERROR(__xludf.DUMMYFUNCTION("""COMPUTED_VALUE"""),"Medium") -> Medium | L49: =IFERROR(__xludf.DUMMYFUNCTION("""COMPUTED_VALUE"""),"027.png") -> 027.png | N49: =IFERROR(__xludf.DUMMYFUNCTION("""COMPUTED_VALUE"""),"Solved") -> Solved | O49: =IFERROR(__xludf.DUMMYFUNCTION("""COMPUTED_VALUE"""),"Front-End") -> Front-End | Q49: =IFERROR(__xludf.DUMMYFUNCTION("""COMPUTED_VALUE"""),"Fahad") -> Fahad
A50: BR-040 | B50: =IFERROR(__xludf.DUMMYFUNCTION("""COMPUTED_VALUE"""),"Subscription") -> Subscription | C50: =IFERROR(__xludf.DUMMYFUNCTION("""COMPUTED_VALUE"""),"Subscription") -> Subscription | D50: =IFERROR(__xludf.DUMMYFUNCTION("""COMPUTED_VALUE"""),"Purchased a yearly plan, but it shows that both the monthly and yearly plans are active.") -> Purchased a yearly plan, but it shows that both the monthly and yearly plans are active. | E50: =IFERROR(__xludf.DUMMYFUNCTION("""COMPUTED_VALUE"""),"User need to able to access website using browser") -> User need to able to access website using browser | F50: =IFERROR(__xludf.DUMMYFUNCTION("""COMPUTED_VALUE"""),"1. Open website of ParentBridge 2. Goto Login Page 3. Login using valid credentials 4. Fill up Basic information 5. Click next and goto subscription page") -> 1. Open website of ParentBridge 2. Goto Login Page 3. Login using valid credentials 4. Fill up Basic information 5. Click next and goto subscription page | G50: =IFERROR(__xludf.DUMMYFUNCTION("""COMPUTED_VALUE"""),"USER CREDENTIAL") -> USER CREDENTIAL | H50: =IFERROR(__xludf.DUMMYFUNCTION("""COMPUTED_VALUE"""),"If the subscription card contains both monthly and yearly data, then when a user purchases a yearly plan, it should not display the current plan as active under the monthly data.") -> If the subscription card contains both monthly and yearly data, then when a user purchases a yearly plan, it should not display the current plan as active under the monthly data. | I50: =IFERROR(__xludf.DUMMYFUNCTION("""COMPUTED_VALUE"""),"Displays both monthly and yearly plans as active on a single subscription card.") -> Displays both monthly and yearly plans as active on a single subscription card. | J50: =IFERROR(__xludf.DUMMYFUNCTION("""COMPUTED_VALUE"""),"Fail") -> Fail | K50: =IFERROR(__xludf.DUMMYFUNCTION("""COMPUTED_VALUE"""),"High") -> High | L50: =IFERROR(__xludf.DUMMYFUNCTION("""COMPUTED_VALUE"""),"028.png") -> 028.png | N50: =IFERROR(__xludf.DUMMYFUNCTION("""COMPUTED_VALUE"""),"Solved") -> Solved | O50: =IFERROR(__xludf.DUMMYFUNCTION("""COMPUTED_VALUE"""),"Front-End") -> Front-End | Q50: =IFERROR(__xludf.DUMMYFUNCTION("""COMPUTED_VALUE"""),"Fahad") -> Fahad
